Workbook

Sheet README
A1: LLM chatbots & dental patient information – systematic review workbook
A3: Title | B3: Accuracy and Safety-Related Limitations of General-Purpose LLM Chatbots for Dental Patient Information: A Systematic Review Across Specialties
A4: Version / date | B4: v1.1 – 2026-10-08 (title/abstract stage completed)
A5: Search date | B5: 2026-10-02 (period 2022-01-01 to 2026-10-02)
A6: Source file | B6: 20261008_LLM_Dental_SR_Raw_Records_before_Deduplication_2026-10-02.xlsx (7,734 raw records, deduplication groups)
A8: Sheet | B8: Content
A9: PICOS_Eligibility | B9: Review questions, PICOS, exclusion reason codes (TA E1–E5, FT FT1–FT8)
A10: Reviewer_Team | B10: Roles and dental backgrounds of R1, R2, R3
A11: Search_Sources | B11: Information sources, search IDs, strategies, record counts (PRISMA-S)
A12: NL_Queries | B12: Natural-language queries used with AI search connectors
A13: PRISMA_Flow | B13: PRISMA 2020 flow numbers (TA stage = live formulas on TA_Screening; FT stage = formulas on FT_Screening)
A14: TA_Screening | B14: Screening sheet: all records with R1/R2 decisions, R3 arbitration, ASReview score/QC, final decision; yellow columns for human validation
A15: Agreement | B15: Inter-reviewer agreement and Cohen's κ per batch and overall
... A30: Legend | B30: Yellow cells = input cells for the team. Grey italic rows = example row showing expected format (delete or overwrite). Dark-blue header rows = fixed.

Sheet PICOS_Eligibility
A1: Review questions and eligibility criteria (PICOS)
A3: Primary question | B3: How accurate is patient-facing dental health information generated by general-purpose large language model chatbots, and what potentially harmful errors or safety-relevant omissions are reported across dental specialties?
A4: Secondary question | B4: To what extent do reported accuracy and safety-related outcomes differ across dental specialties, and how are these differences associated with model version, task characteristics, and evaluation methods?
A6: Element | B6: Definition for this review | C6: Operationalisation / notes
A7: P – Population (information need) | B7: Dental, oral and maxillofacial health information needs of patients, parents/caregivers and the lay public, in any dental specialty. | C7: Patient FAQs, patient-style questions, lay scenarios (e.g. dental trauma first aid), patient education topics. Specialties coded a priori: OMFS/dentoalveolar surgery, orthodontics, endodontics, periodontology, prosthodontics, implantology, paediatric dentistry, restorative dentistry/cariology, oral medicine/pathology incl. oral cancer, TMD/orofacial pain, dental trauma, preventive/community oral health, oral radiology, cleft lip/palate, dental sleep medicine, multi-specialty/general dentistry.
A8: I – Index technology | B8: General-purpose, publicly available LLM chatbots used as released (web interface, app or API). | C8: ChatGPT (GPT-3.5, GPT-4, GPT-4o, o-series, GPT-5), Gemini/Bard, Microsoft Copilot/Bing Chat, Claude, Llama/Meta AI, Perplexity, DeepSeek, Mistral/Le Chat, Grok, ERNIE Bot, Qwen and comparable systems. Custom GPTs, RAG or fine-tuned models are eligible comparators but only general-purpose arms enter the primary synthesis.
A9: C – Comparator | B9: Not required. | C9: If present: other LLMs/versions, dentists/specialists, professional websites, guidelines, search engines.
A10: O – Outcomes | B10: Primary: accuracy (correctness) of LLM-generated content; potentially harmful errors; safety-relevant omissions. | C10: Secondary: completeness, overall/content quality (GQS, DISCERN, EQIP), guideline concordance, readability (FRE, FKGL, SMOG), understandability/actionability (PEMAT), consistency/reproducibility, empathy, inter-rater reliability. A study must report ≥1 primary outcome (accuracy or a safety outcome) to be included.
A11: S – Study design | B11: Primary empirical evaluation studies (cross-sectional/in-silico, comparative or observational) with original data. | C11: Full articles and research letters/short communications with original data in peer-reviewed journals. Excluded: reviews, editorials, commentaries, letters without data, protocols, conference abstracts, book chapters, errata, questionnaire surveys of perceptions.
A12: Timeframe / language | B12: Published 1 January 2022 – 2 October 2026 (de facto from the release of ChatGPT, 30 November 2022). | C12: No restriction on the language of the chatbot query. Full texts in English or German assessed directly; other languages via verified machine translation.
A15: Code | B15: Title/abstract stage (TA) | C15: Full-text stage (FT)
A16: E1 / FT1 | B16: Not a dental, oral or maxillofacial topic | C16: Not a dental, oral or maxillofacial topic
A17: E2 / FT2 | B17: Not a general-purpose LLM chatbot (other AI, rule-based bot, only domain-specific model) | C17: No extractable general-purpose LLM arm
A18: E3 / FT3 | B18: Not patient-facing (exam/MCQ, professional decision support, image diagnosis, education, research use) | C18: Patient-facing subset not identifiable or not separately reported
A19: E4 / FT4 | B19: No content evaluation of LLM output (e.g. readability only, perceptions survey) | C19: No accuracy or safety outcome reported (or not extractable)
... A35: S9 | B35: Inconsistency with safety impact | C35: Contradictory advice across repetitions or model versions

Sheet Reviewer_Team
A1: Reviewer team
A3: Role | B3: Reviewer profile (dental background) | C3: Task
A4: Reviewer 1 (R1) | B4: Oral and maxillofacial surgeon (DMD, MD); dentoalveolar and implant surgery, oral oncology, TMJ; research on patient information and informed consent | C4: Independent title/abstract screening of all records (calibration + main round)
A5: Reviewer 2 (R2) | B5: Orthodontist and paediatric dentist (DDS, MSc) with postgraduate training in dental public health; research on oral-health literacy, readability and quality of online patient information (DISCERN, PEMAT) | C5: Independent title/abstract screening of all records (calibration + main round)
A6: Reviewer 3 (R3) | B6: Periodontist and restorative dentist; senior evidence-based-dentistry methodologist (systematic review and GRADE experience) | C6: Arbitration of all conflicts and UNSURE records; safety re-check of records flagged by the ASReview quality control

Sheet Search_Sources
A1: Information sources and search strategies (PRISMA-S)
A3: Source | B3: Search ID | C3: Strategy (see note) | D3: Records retrieved | E3: Date searched | F3: Date limits | G3: Other limits
A4: PubMed/MEDLINE | B4: PM-01 | C4: C1 AND C2 in [tiab]/MeSH; 2022/01/01:2026/10/02[dp]. Reconstructed logic: (ChatGPT OR "large language model" OR chatbot OR "generative AI" OR GPT-4 OR Gemini OR Bard OR Copilot OR Claude OR DeepSeek OR Llama OR Perplexity)[tiab] AND (dental OR dentistry OR dentist OR "oral health" OR orthodontic OR endodontic OR periodontal OR prosthodontic OR "oral surgery" OR maxillofacial OR "dental implant" OR "pediatric dentistry" OR caries OR teeth)[tiab] – verify verbatim string | D4: 1315 | E4: 2026-10-02 | F4: 2022-01-01 – 2026-10-02 | G4: none
A5: Europe PMC (+ preprints) | B5: EP-01 | C5: C1 AND C2 (TITLE_ABS/KW); FIRST_PDATE:[2022-01-01 TO 2026-10-02]; SRC incl. PPR | D5: 1400 | E5: 2026-10-02 | F5: 2022-01-01 – 2026-10-02 | G5: none
A6: Semantic Scholar | B6: S2-01 | C6: C1 AND C2 (title/abstract), year 2022–2026 | D6: 1903 | E6: 2026-10-02 | F6: 2022-01-01 – 2026-10-02 | G6: none
A7: Crossref | B7: CR-01..CR-120 | C7: 120 pairwise C1 term × C2 term queries (query.bibliographic), from-pub-date 2022-01-01; local filter C1∧C2 in title/abstract/keywords | D7: 694 | E7: 2026-10-02 | F7: 2022-01-01 – 2026-10-02 | G7: none
A8: DOAJ | B8: DJ-01 | C8: C1 AND C2 (bibjson.title/abstract/keywords), 2022–2026 | D8: 1018 | E8: 2026-10-02 | F8: 2022-01-01 – 2026-10-02 | G8: none
A9: arXiv | B9: AX-01 | C9: all: C1 AND C2, submittedDate 2022–2026 | D9: 54 | E9: 2026-10-02 | F9: 2022-01-01 – 2026-10-02 | G9: none
A10: Amass BiomedCore | B10: AM01, AM02, Q01–Q15 | C10: AM01: (ChatGPT OR "large language model" OR chatbot OR "generative AI" OR GPT-4 OR Gemini OR Bard OR Copilot OR Claude OR DeepSeek OR Llama OR Perplexity) AND (dental OR dentistry OR dentist OR "oral health" OR orthodontic OR endodontic OR periodontal OR prosthodontic OR "oral surgery" OR maxillofacial OR "dental implant" OR "pediatric dentistry" OR caries OR teeth); AM02 focused (see S1a); Q01–Q15 natural language | D10: 850 | E10: 2026-10-02 | F10: 2022-01-01 – 2026-10-02 | G10: none
A11: Wiley Scholar Gateway | B11: Q01–Q15 | C11: Natural-language full-text queries (S1c); passages mapped to articles | D11: 300 | E11: 2026-10-02 | F11: 2022-01-01 – 2026-10-02 | G11: none
A12: Consensus | B12: Q01–Q20 | C12: Natural-language queries (S1c); first author only, matched by title | D12: 200 | E12: 2026-10-02 | F12: 2022-01-01 – 2026-10-02 | G12: none
A13: Elicit | B13: – | C13: Q01–Q20 attempted; refused (no API access) | D13: 0 | E13: 2026-10-02 | F13: 2022-01-01 – 2026-10-02 | G13: none
C14: Total | D14: =SUM(D4:D13) -> 7734
A16: Concept block C1 (LLM/chatbot): (ChatGPT OR "large language model" OR chatbot OR "generative AI" OR GPT-4 OR Gemini OR Bard OR Copilot OR Claude OR DeepSeek OR Llama OR Perplexity)
A17: Concept block C2 (dentistry): (dental OR dentistry OR dentist OR "oral health" OR orthodontic OR endodontic OR periodontal OR prosthodontic OR "oral surgery" OR maxillofacial OR "dental implant" OR "pediatric dentistry" OR caries OR teeth)
A18: Verbatim database syntax is stored in sheet Search_Strategy of LLM_Dental_SR_Search_Results_2026-10-02.xlsx – paste here before submission.
A19: Pending complementary searches: Scopus, Web of Science Core Collection, Embase, IEEE Xplore, Google Scholar (first 200), backward/forward citation searching.
A22: Source | B22: Raw records | C22: Retained as primary record | D22: Removed as duplicate | E22: Raw records in screening-set groups
A23: Amass BiomedCore (connector) | B23: 850 | C23: 373 | D23: 477 | E23: 459
A24: Consensus (connector) | B24: 200 | C24: 11 | D24: 189 | E24: 192
A25: Crossref | B25: 694 | C25: 228 | D25: 466 | E25: 669
A26: DOAJ | B26: 1018 | C26: 456 | D26: 562 | E26: 596
A27: Europe PMC | B27: 1294 | C27: 2 | D27: 1292 | E27: 1294
A28: Europe PMC (Preprint) | B28: 106 | C28: 82 | D28: 24 | E28: 106
A29: PubMed/MEDLINE | B29: 1315 | C29: 1315 | D29: 0 | E29: 1315
A30: Semantic Scholar | B30: 1903 | C30: 520 | D30: 1383 | E30: 1903
A31: Wiley Scholar Gateway (connector, full text) | B31: 300 | C31: 57 | D31: 243 | E31: 218
A32: arXiv | B32: 54 | C32: 11 | D32: 43 | E32: 43

Sheet NL_Queries
A1: Natural-language queries (semantic connectors)
A3: ID | B3: Query | C3: Connectors
A4: Q01 | B4: accuracy of ChatGPT responses to dental patient questions | C4: Consensus; Amass; Wiley
A5: Q02 | B5: large language model chatbots patient information dentistry accuracy and safety | C5: Consensus; Amass; Wiley
A6: Q03 | B6: ChatGPT orthodontics patient questions accuracy | C6: Consensus; Amass; Wiley
A7: Q04 | B7: chatbot endodontics root canal treatment patient information quality | C7: Consensus; Amass; Wiley
A8: Q05 | B8: large language model periodontology periodontal disease patient education | C8: Consensus; Amass; Wiley
A9: Q06 | B9: ChatGPT oral and maxillofacial surgery third molar extraction patient information | C9: Consensus; Amass; Wiley
A10: Q07 | B10: chatbot pediatric dentistry parents questions accuracy | C10: Consensus; Amass; Wiley
A11: Q08 | B11: large language model dental implants patient questions | C11: Consensus; Amass; Wiley
A12: Q09 | B12: ChatGPT prosthodontics dentures patient information | C12: Consensus; Amass; Wiley
A13: Q10 | B13: Gemini Bard Copilot chatbots comparison dental questions | C13: Consensus; Amass; Wiley
A14: Q11 | B14: readability and reliability of AI chatbot responses about oral health | C14: Consensus; Amass; Wiley
... A23: Q20 | B23: large language model cleft lip palate patient information | C23: Consensus

Sheet TA_Screening
A1: Record ID | B1: Screening order | C1: Batch | D1: Title | E1: Abstract | F1: Authors | G1: Year | H1: Journal | I1: DOI | J1: PMID | K1: Publication type | L1: Language | M1: Specialty flag (rule-based) | N1: Sources | O1: R1 decision | P1: R1 code | Q1: R1 note | R1: R2 decision | S1: R2 code | T1: R2 note | U1: R1/R2 agreement | V1: R3 decision | W1: R3 code | X1: R3 rationale | Y1: ASReview OOF score | Z1: ASReview rank | AA1: QC flag | AB1: QC R3 decision | AC1: QC R3 rationale | AD1: Final TA decision | AE1: Final exclusion code | AF1: Decision basis | AG1: Human validation (Agree/Disagree) | AH1: Human validator | AI1: Validation comment
A2: LLMDENT-1819 | B2: 1 | C2: calibration | D2: Is the field of endodontics prepared to utilise ChatGPT? | F2: Maltarollo, Thalya Fernanda Horsth; Strazzi-Sahyon, Henrico Badaoui; Amaral, Rodrigo Rodrigues; Sivieri-Araújo, Gustavo | G2: 2024 | H2: Australian endodontic journal : the journal of the Australian Society of Endodontology Inc | I2: 10.1111/aej.12821 | J2: 37994592.0 | K2: Letter / comment / editorial | L2: English | M2: Endodontics | N2: Crossref; Europe PMC; PubMed/MEDLINE; Semantic Scholar | O2: EXCLUDE | P2: E5 | Q2: letter/comment on ChatGPT in endodontics; no abstract; no data apparent | R2: EXCLUDE | S2: E5 | T2: letter/comment no abstract; no evaluation data indicated | U2: =IF(AND(O2=R2,O2<>"UNSURE"),"Agree","Conflict/Unsure") -> Agree | Y2: 0.145 | Z2: 1526 | AA2: No | AD2: EXCLUDE | AE2: E5 | AF2: R1 = R2
A3: LLMDENT-2095 | B3: 2 | C3: calibration | D3: Role of Dental Pulp Stem Cells to Promote Angiogenesis in Cell-based Regenerative Endodontics. | E3: Maintaining the viability and avoiding necrosis of dental pulp are crucial to preserving the structural integrity and functioning of teeth. In recent years, cell-based regenerative endodontics has emerged as a promising approach to achieve this goal and has gained increasing attention in scientific research; however, in the confined space of the root canal system, hypoxic conditions can be both beneficial and detrimental, as they may promote angiogenesis in the graft to some extent but also lead to tissue necrosis if prolonged. Dental pulp stem cells (DPSCs) have been verified as multipotent cells that can promote angiogenesis and are therefore ideal candidates for realising real dental pulp regeneration within root canals. Thus, we focus on the underlying mechanisms of DPSCs to promote angiogenesis and summarise some preclinical studies and clinical trials involving transplanting of DPSCs to achieve real dental pulp regeneration, in the hope that this intractable source of perplexity in regenerative endodontics may be resolved sooner. | F3: Tang, Meng Qi; Ye, Ling; Gao, Bo | G3: 2023 | H3: The Chinese journal of dental research | I3: 10.3290/j.cjdr.b4330823 | J3: 37732679.0 | K3: Journal article (original research) | L3: English | M3: Endodontics | N3: Europe PMC; PubMed/MEDLINE; Semantic Scholar | O3: EXCLUDE | P3: E2 | Q3: dental pulp stem cells; no LLM | R3: EXCLUDE | S3: E2 | T3: dental pulp stem cells review; no LLM | U3: =IF(AND(O3=R3,O3<>"UNSURE"),"Agree","Conflict/Unsure") -> Agree | Y3: 0.05 | Z3: 1971 | AA3: No | AD3: EXCLUDE | AE3: E2 | AF3: R1 = R2
A4: LLMDENT-1762 | B4: 3 | C4: calibration | D4: Hygiea+: Toward Energy-Efficient and Highly Accurate Toothbrushing Monitoring via Wrist-Worn Gesture Sensing | E4: Proper and effective toothbrushing technique is crucial for maintaining oral health. However, there are often limited opportunities for individuals to receive specific training in toothbrushing posture in their daily lives. In this article, we propose Hygiea+, a convenient, energy-efficient, and highly accurate toothbrushing monitoring system based on wrist-worn wearables. By leveraging inertial measurement units (IMUs) in wrist-worn devices for gesture sensing, Hygiea+ enables users to accurately and efficiently monitor their toothbrushing activities without any modifications to the toothbrush. We propose a number of novel techniques to achieve the goal of high sensing accuracy and energy efficiency. To reduce the energy consumption of continuous IMU sampling, we model the sensing problem as a Markov process and design a partially observable Markov decision process (POMDP)-based adaptive sampling strategy to dynamically adjust the sampling frequency. To achieve high sensing accuracy, we first propose a novel signal preprocessing method to mitigate variations resulting from different toothbrush types and user habits. Then, we propose a deep reinforcement learning-based data distillation mechanism to extract key segments from continuous toothbrushing actions, thus reducing the impact of redundant data and noise. In the classification stage, we design an attention-based long short-term memory (AT-LSTM) network for fine-grained toothbrushing posture recognition. In addition, to … | F4: Xingyu Feng; Chengwen Luo; Junliang Chen; Jianqiang Li; Li Zhang; Zahir Tari; Wei-Tao Xu | G4: 2024 | H4: IEEE Internet of Things Journal | I4: 10.1109/jiot.2024.3439194 | K4: Journal article (original research) | L4: English (automatically detected) | M4: Preventive dentistry / dental public health | N4: Semantic Scholar | O4: EXCLUDE | P4: E2 | Q4: wearable toothbrushing sensing system; LLM only feedback add-on | R4: EXCLUDE | S4: E2 | T4: wearable toothbrushing sensing system; LLM only add-on feedback | U4: =IF(AND(O4=R4,O4<>"UNSURE"),"Agree","Conflict/Unsure") -> Agree | Y4: 0.079 | Z4: 1862 | AA4: No | AD4: EXCLUDE | AE4: E2 | AF4: R1 = R2
A5: LLMDENT-1406 | B5: 4 | C5: calibration | D5: SPECTRUM SRA: An R Shiny Application to Automate Systematic Reviews Using Artificial Intelligence and Large Language Models | E5: Abstract Purpose : This study aims to develop an R Shiny application named SPECTRUM SRA (Systematic Review Automation) and to assess its feasibility. The application encompasses eight modules: Search, PRISMA flow diagram generation, dEduplication, sCreening, daTa extraction, Reporting, qUery, and suMmarization. It provides an end‑to‑end workflow to automate and semi‑automate multiple steps of systematic reviews, addressing growing time and labor constraints and accelerating evidence‑to‑practice translation. Design/methodology/approach : SPECTRUM SRA comprises eight interconnected modules and offers an interface for automated article search and retrieval from PubMed, Scopus, and Web of Science. Search functionality is implemented via API integration for PubMed and Scopus, with manual search and import for Web of Science results. Deduplication employs two strategies: DOI‑based matching and fuzzy string deduplication. The application also supports automated title/abstract and full‑text screening using large language model prompting. Automated reporting for both search and screening is incorporated through AI‑driven scripting. Additionally, SPECTRUM SRA automates PRISMA flow diagram generation. Summarization and data extraction of the final set of eligible studies are performed via LLM prompting. The feasibility of the application was assessed through a systematic review of randomized controlled trials comparing virtual reality interventions to non‑virtual‑reality approaches in d… | F5: Nezhad HM; CheshmehSohrabi M | G5: 2025 | H5: Research Square | I5: 10.21203/rs.3.rs-7265470/v1 | K5: Preprint | L5: English (automatically detected) | M5: Oral & maxillofacial surgery | N5: Europe PMC (Preprint) | O5: EXCLUDE | P5: E2 | Q5: LLM as systematic review automation tool | R5: EXCLUDE | S5: E2 | T5: LLM as systematic review automation research tool | U5: =IF(AND(O5=R5,O5<>"UNSURE"),"Agree","Conflict/Unsure") -> Agree | Y5: 0.02 | Z5: 2052 | AA5: No | AD5: EXCLUDE | AE5: E2 | AF5: R1 = R2
A6: LLMDENT-2157 | B6: 5 | C6: calibration | D6: Perplexity and Repercussions in Maldiagnosis of an Extraoral Draining Sinus by a Physician and its Dental Management: A Case Report. | E6: UNLABELLED: The cutaneous sinus of dental origin represents a skin disorder that appears due to an infection accompanied by bony changes. The remote location of the lesion relative to the primary site of the disease leads to its presumption of a skin etiology by the individual. Inadequate knowledge on the part of the physician followed by faulty management complicates the situation further. However, unless the dental cause is not addressed, the lesion does not resolve. The following case report discusses the dental management of an extraoral sinus with the aim of guiding the general public, physicians, and dentists with its accurate and timely assessment so as to avoid additional financial costs, futile antibiotic therapy courses, and unnecessary surgical excisions. HOW TO CITE THIS ARTICLE: Sidhu S, Thomas AM, Kundra R. Perplexity and Repercussions in Maldiagnosis of an Extraoral Draining Sinus by a Physician and its Dental Management: A Case Report. Int J Clin Pediatr Dent 2022;15(1):115-118. | F6: Sidhu, Seerat; Thomas, Abi M; Kundra, Ruchika | G6: 2022 | H6: International journal of clinical pediatric dentistry | I6: 10.5005/jp-journals-10005-2349 | J6: 35528484.0 | K6: Journal article (original research) | L6: English | M6: Dental pharmacology / anesthesia | N6: Crossref; Europe PMC; PubMed/MEDLINE; Semantic Scholar | O6: EXCLUDE | P6: E2 | Q6: case report; no LLM | R6: EXCLUDE | S6: E2 | T6: clinical case report; no LLM | U6: =IF(AND(O6=R6,O6<>"UNSURE"),"Agree","Conflict/Unsure") -> Agree | Y6: 0.136 | Z6: 1576 | AA6: No | AD6: EXCLUDE | AE6: E2 | AF6: R1 = R2
A7: LLMDENT-0625 | B7: 6 | C7: calibration | D7: A cross-sectional evaluation of Large Language Model answers to dental questions. | E7: BACKGROUND: Patients increasingly turn to the Internet and, more recently, to Large Language Models (LLMs) to seek answers to dental questions. However, the safety of LLM-generated dental advice for patients has not been systematically assessed. METHODS: Thirty dental questions spanning six disciplines were developed and posed in Polish and English to six LLMs. Each question was answered five times per model per language, yielding 2,700 unique LLM-generated answers, each independently evaluated by two dentists. A binary text classifier combining Qwen3-Embedding-0.6B word embeddings with a Support Vector Machine (SVM) was trained on 1,680 labeled answers and evaluated on 420 held-out answers. RESULTS: Substantial inter-rater agreement on harmfulness was observed (Cohen's [Formula: see text]). Without a system prompt, 56% of outputs from gpt-4o, gpt-4o-mini, and llama-3.3-70b were classified as harmful (pooling both languages; a question was counted as harmful if at least one of its five generated answers was labeled harmful by at least one annotator). A safety-oriented system prompt reduced this rate by 26 percentage points to 30%. llama-3.3-70b showed markedly higher harmfulness in Polish than English ([Formula: see text], [Formula: see text]). The trained classifier showed a tendency to mark non-harmful answers as harmful, though performance was lower for Polish than English outputs. CONCLUSIONS: Publicly available LLMs can pose potential safety risks to dental patients when… | F7: Mysior, Martyna; Mysior, Marek Piotr; Maslowski, Pamela; Skośkiewicz-Malinowska, Katarzyna | G7: 2026 | H7: BMC oral health | I7: 10.1186/s12903-026-09223-4 | J7: 42432645.0 | K7: Journal article (original research) | L7: English | M7: General dentistry / cross-specialty | N7: Amass BiomedCore (connector); Crossref; Europe PMC; PubMed/MEDLINE; Semantic Scholar | O7: INCLUDE | P7: - | Q7: dental advice for patients; six LLMs; harmfulness rated by dentists | R7: INCLUDE | S7: - | T7: patient dental questions; six LLMs; harmfulness rated by dentists | U7: =IF(AND(O7=R7,O7<>"UNSURE"),"Agree","Conflict/Unsure") -> Agree | Y7: 0.421 | Z7: 589 | AA7: No | AD7: INCLUDE | AE7: - | AF7: R1 = R2
A8: LLMDENT-1105 | B8: 7 | C8: calibration | D8: Accuracy of Artificial Intelligence in Making Diagnoses and Treatment Decisions in Pediatric Dentistry. | E8: Purpose: To assess the diagnostic and treatment decision-making accuracy of ChatGPT for various dental problems in pediatric patients compared to specialized pediatric dentists. Methods: This study included 12 cases, each with an average of three dental problems, resulting in a total of 36 dental problems. Successive prompts were given to ChatGPT (GPT-4), beginning with a comprehensive case presentation, followed by clinical and radiographic descriptions alongside clinical and radiographic images. Inputs for questions regarding the diagnosis and treatment were provided to the models. Accuracy was then scored based on the degree of alignment between the ChatGPT outputs and the pediatric dentistry committee decisions, which represented the control group based on their advanced training and clinical experience. Results: ChatGPT's diagnostic accuracy was 72.2 percent, with a kappa statistic of 0.69 (95 percent confidence interval [95% CI] equals 0.6 to 0.8). In detecting dental caries, ChatGPT achieved a sensitivity of 92.3 percent and a specificity of 100 percent, with positive and negative predictive values of 100 percent and 83.3 percent, respectively. ChatGPT's treatment decision accuracy was 47.2 percent with a kappa value of 0.43 (95% CI equals 0.4 to 0.6). The difference between the accuracy of ChatGPT in diagnosis and treatment decisions was statistically significant (P=0.01). Conclusions: ChatGPT achieved high diagnostic accuracy but had limited capability in making trea… | F8: Bhadila, Ghalia Y; Alhomied, Mody; Mahmoud, Abeer; Farsi, Nada J | G8: 2025 | H8: Pediatric dentistry | J8: 40296263.0 | K8: Journal article (original research) | L8: English | M8: Pediatric dentistry; Restorative dentistry / cariology; Oral & maxillofacial radiology | N8: Europe PMC; PubMed/MEDLINE; Semantic Scholar | O8: EXCLUDE | P8: E3 | Q8: GPT-4 diagnosis/treatment decisions pediatric cases with images | R8: EXCLUDE | S8: E3 | T8: pediatric case diagnosis/treatment decisions with images | U8: =IF(AND(O8=R8,O8<>"UNSURE"),"Agree","Conflict/Unsure") -> Agree | Y8: 0.299 | Z8: 873 | AA8: No | AD8: EXCLUDE | AE8: E3 | AF8: R1 = R2
A9: LLMDENT-0972 | B9: 8 | C9: calibration | D9: Author Correction: Towards clinical-level interpretation of dental panoramic radiography using an instance-guided vision-language model. | F9: Zhu, Qikui; Lin, Yeyu; Fu, Weitao; Tang, Wenhui; Li, Jiaxing; Zhang, Ying; Li, Bo; Guo, Xiaolong; Wang, Fang; Qi, Haiyan; Sun, Chongke; Zhu, Xiangkui; Liu, Zhonghao; He, Li; Zheng, Zhiguo; Du, Bo; Yan | G9: 2026 | H9: Nature biomedical engineering | I9: 10.1038/s41551-026-01759-8 | J9: 42420428.0 | K9: Erratum / correction | L9: English | M9: Oral & maxillofacial radiology | N9: Europe PMC; PubMed/MEDLINE; Semantic Scholar | O9: EXCLUDE | P9: E2 | Q9: erratum; custom vision-language model panoramic radiographs | R9: EXCLUDE | S9: E2 | T9: erratum; dental radiograph vision-language model | U9: =IF(AND(O9=R9,O9<>"UNSURE"),"Agree","Conflict/Unsure") -> Agree | Y9: 0.053 | Z9: 1960 | AA9: No | AD9: EXCLUDE | AE9: E2 | AF9: R1 = R2
A10: LLMDENT-0959 | B10: 9 | C10: calibration | D10: SegORG: Report Generation of Oral Potentially Malignant Disorders Image Based on Lesion Segmentation-Enhanced LLM. | E10: OBJECTIVES: To develop an automated system for generating standardized reports for oral potentially malignant disorders (OPMDs) from white-light images, aiming to reduce documentation workload, facilitate early intervention, and enable longitudinal lesion monitoring. METHODS: We proposed the SegORG model using 441 oral mucosa images and 1323 corresponding reports. It employed SegFormer for lesion segmentation; a visual encoder extracted global and local visual embeddings, which were projected into a pre-trained large language model (LLM feature) space via a lightweight visual mapper. The Qwen2.5-7B model then generated structured diagnostic reports, enhanced by text augmentation techniques to improve diversity and professionalism. RESULTS: SegORG achieved BLEU-4, ROUGE-L, and CIDEr scores of 0.291, 0.517, and 0.578, respectively. Additionally, the model obtained a clinical diagnostic F1-score of 0.695 and a median expert rating of 4 on the Likert scale (p < 0.001). It significantly outperformed conventional baseline models (R2Gen, METransformer, and SwinB+BERT9k) and contemporary general-purpose multimodal LLMs (GPT-4, Gemini 2.5 Pro, and Qwen2.5-VL), despite its lean architecture (90.4 M trainable parameters). CONCLUSIONS: By enhancing visual feature extraction and achieving efficient text alignment, SegORG offers an effective technical pathway for OPMDs reports automation. While single-center validation shows promise, multicenter trials are needed to assess generalizability… | F10: Zhang, Rui; Huang, Peng; Ding, Tingting; Chen, Yaowu; Tian, Xiang; Cao, Yuqi; Chen, Wei; Chen, Xiaoyan; Chen, Qianming; Zhu, Fudong | G10: 2026 | H10: Oral diseases | I10: 10.1111/odi.70148 | J10: 41313616.0 | K10: Journal article (original research) | L10: English | M10: Oral & maxillofacial surgery; Oral medicine / oral pathology | N10: Europe PMC; PubMed/MEDLINE | O10: EXCLUDE | P10: E3 | Q10: OPMD image report generation; diagnostic task | R10: EXCLUDE | S10: E3 | T10: image-based OPMD report generation; diagnostic/documentation task | U10: =IF(AND(O10=R10,O10<>"UNSURE"),"Agree","Conflict/Unsure") -> Agree | Y10: 0.16 | Z10: 1444 | AA10: No | AD10: EXCLUDE | AE10: E3 | AF10: R1 = R2
A11: LLMDENT-0968 | B11: 10 | C11: calibration | D11: High-Fidelity and Lip-Synced Talking Face Synthesis via Landmark-Based Diffusion Model. | E11: Audio-driven talking face video generation has attracted increasing attention due to its huge industrial potential. Some previous methods focus on learning a direct mapping from audio to visual content. Despite progress, they often struggle with the ambiguity of the mapping process, leading to flawed results. An alternative strategy involves facial structural representations (e.g., facial landmarks) as intermediaries. This multi-stage approach better preserves the appearance details but suffers from error accumulation due to the independent optimization of different stages. Moreover, most previous methods rely on generative adversarial networks, prone to training instability and mode collapse. To address these challenges, our study proposes a novel landmark-based diffusion model for talking face generation, which leverages facial landmarks as intermediate representations while enabling end-to-end optimization. Specifically, we first establish the less ambiguous mapping from audio to landmark motion of lip and jaw. Then, we introduce an innovative conditioning module called TalkFormer to align the synthesized motion with the motion represented by landmarks via differentiable cross-attention, which enables end-to-end optimization for improved lip synchronization. Besides, TalkFormer employs implicit feature warping to align the reference image features with the target motion for preserving more appearance details. Extensive experiments demonstrate that our approach can synthesi… | F11: Zhong, Weizhi; Lin, Junfan; Chen, Peixin; Gao, Feng; Lin, Liang; Li, Guanbin | G11: 2026 | H11: IEEE transactions on image processing : a publication of the IEEE Signal Processing Society | I11: 10.1109/tip.2026.3676251 | J11: 41886322.0 | K11: Journal article (original research) | L11: English | M11: General dentistry / cross-specialty | N11: Europe PMC; PubMed/MEDLINE | O11: EXCLUDE | P11: E1 | Q11: talking face video synthesis; not dental | R11: EXCLUDE | S11: E1 | T11: talking face video synthesis; not dental | U11: =IF(AND(O11=R11,O11<>"UNSURE"),"Agree","Conflict/Unsure") -> Agree | Y11: 0.003 | Z11: 2090 | AA11: No | AD11: EXCLUDE | AE11: E1 | AF11: R1 = R2
A12: LLMDENT-1607 | B12: 11 | C12: calibration | D12: ProtBERT-Based Prediction of Functional TRPV Sequences for Oral Cancer Pain | E12: Background and Objectives: Oral Cancer often leads to opioid tolerance, affecting pain-sensing neurons. TRPV ion channels, which are activated by inflammatory molecules, can be agonists or antagonists. Cancer changes the peripheral and central nervous systems, affecting tumor interactions, nociceptors, and the immune system. Activation of these receptors triggers pain perception and second messengers. Antagonists alleviate cancer-induced pain, suggesting therapeutic approaches. This study uses a large language model to find and forecast functional TRPV sequences for oral cancer pain. Materials and Methods: TRPV proteins were obtained from UniProt; id -Q8NER1, Q9HBA0, Q9NQA5, Q9H1D0, and Q9Y5S1 were identified and quality-checked. Deepbio analyzed FASTA sequences. Large language models and sequence prediction techniques were used for prediction and classification, including Protbert (a pre-trained protein sequence model), BiLSTM, LSTMAttention, and TextRGNN (a residual graph neural network). Results: The study reveals that ProtBERT and BiLSTM are the best predictors of amino acid sequences for TRPV1-based oral cancer, offering a balance of sensitivity and specificity. The ProtBERT model effectively identifies positive and negative cases related to TRPV with an accuracy of 0.90, a sensitivity of 0.89, a specificity of 0.91, and an AUC of 0.937. The BiLSTM model, similar to ProtBERT, has high accuracy and sensitivity, while the LSTM Attention model is reliable in detecting true … | F12: P. Yadalam | G12: 2025 | H12: The Journal of Basic and Clinical Dentistry | I12: 10.64471/30rcas82 | K12: Journal article (original research) | L12: English (automatically detected) | M12: Oral medicine / oral pathology | N12: Semantic Scholar | O12: EXCLUDE | P12: E2 | Q12: ProtBERT protein sequence prediction; not chatbot | R12: EXCLUDE | S12: E2 | T12: ProtBERT protein sequence prediction; not chatbot | U12: =IF(AND(O12=R12,O12<>"UNSURE"),"Agree","Conflict/Unsure") -> Agree | Y12: 0.183 | Z12: 1338 | AA12: No | AD12: EXCLUDE | AE12: E2 | AF12: R1 = R2
A13: LLMDENT-0316 | B13: 12 | C13: calibration | D13: From reviews to real-time: dynamic evidence in dentistry. | E13: BACKGROUND: The exponential growth of biomedical literature-over a million new PubMed entries each year-has outpaced traditional evidence-synthesis methods. Systematic reviews, long the cornerstone of evidence-based dentistry, are resource-intensive and often outdated within a few years, widening the gap between current research and clinical practice. METHODS: We outline Retrieval-Augmented Generation (RAG) as a methodology for dynamic evidence reviews. RAG strengthens Large Language Models (LLMs) by combining their generative capacity with real-time retrieval from a continuously updated, curated knowledge base. This design grounds every answer in verifiable sources and mitigates the factual errors and hallucinations seen in standalone LLMs. RESULTS/IMPLICATIONS: RAG enables on-demand dynamic synthesis of the latest evidence, allowing clinicians and researchers to ask complex, natural-language questions and receive concise, fully cited answers. For dental clinicians, this approach enables rapid, citation-linked answers to practice-relevant questions-such as material selection, healing outcomes, or procedural comparisons-without relying on outdated narrative summaries. We describe three complementary integration pathways-RAG on pre-retrieved article pools, public living review portals, and machine-actionable journal publications-each with distinct requirements and benefits. Looking forward, emerging agentic AI systems, capable of planning multi-step searches and iterative upda… | F13: Gavrilova, A V; Galli, C | G13: 2026 | H13: Evidence-based dentistry | I13: 10.1038/s41432-026-01206-2 | J13: 41735601.0 | K13: Journal article (original research) | L13: English | M13: General dentistry / cross-specialty | N13: Europe PMC; PubMed/MEDLINE; Semantic Scholar | O13: EXCLUDE | P13: E2 | Q13: RAG methodology for evidence synthesis; conceptual; clinicians/researchers | R13: EXCLUDE | S13: E2 | T13: conceptual RAG framework for evidence synthesis; no chatbot evaluation | U13: =IF(AND(O13=R13,O13<>"UNSURE"),"Agree","Conflict/Unsure") -> Agree | Y13: 0.045 | Z13: 1981 | AA13: No | AD13: EXCLUDE | AE13: E2 | AF13: R1 = R2
A14: LLMDENT-0500 | B14: 13 | C14: calibration | D14: Evaluation of large language models in root resorption scenarios: an ESE-aligned comparative performance assessment. | E14: This study aims to compare the diagnostic accuracy, appropriateness of treatment planning, and source citation performance of five large language models ChatGPT-4o (Free), ChatGPT-5.1 Plus, Microsoft Copilot, Google Gemini, and DeepSeek-R1 in root resorption scenarios. In December 2025, twelve clinical scenarios were created based on the classification of the European Society of Endodontology and each scenario was presented to all chatbots over four consecutive days. All responses were evaluated using a blinded assessment protocol and a binary scoring system. A total of 720 observations (12 cases × 4 repetitions × 3 criteria per model) were analyzed. The collected data were analyzed using chi-square, Fisher's exact, and Cochran Q tests. In terms of diagnostic accuracy, Microsoft Copilot (79.2%), ChatGPT-5.1 (77.1%), and ChatGPT-4o (Free) (75%) showed the highest performance. Google Gemini (68.8%) demonstrated a moderate level of accuracy, while DeepSeek (39.6%) showed markedly low performance. All models exhibited high accuracy in treatment plan recommendations, and no statistically significant differences were detected. Regarding citation accuracy, Copilot ranked first with 100% accuracy. Although large language models present potential as supportive decision-making tools in the evaluation of root resorption, diagnostic inconsistencies, limitations in source accuracy, and variability in responses restrict their independent use in clinical applications. Therefore, the outputs… | F14: Keleş, Öznur Küçük; Arslan, Zeynep Betül | G14: 2026 | H14: Odontology | I14: 10.1007/s10266-026-01531-z | J14: 42573919.0 | K14: Journal article (original research) | L14: English | M14: Endodontics | N14: Europe PMC; PubMed/MEDLINE; Semantic Scholar | O14: EXCLUDE | P14: E3 | Q14: root resorption clinical scenarios; diagnosis and treatment planning | R14: EXCLUDE | S14: E3 | T14: root resorption clinical scenarios; diagnosis and treatment planning | U14: =IF(AND(O14=R14,O14<>"UNSURE"),"Agree","Conflict/Unsure") -> Agree | Y14: 0.445 | Z14: 546 | AA14: No | AD14: EXCLUDE | AE14: E3 | AF14: R1 = R2
A15: LLMDENT-1556 | B15: 14 | C15: calibration | D15: Evaluation of artificial intelligence robot's knowledge and reliability on dental implants and peri-implant phenotype. | E15: Abstract The aim of this study was to evaluate the reliability and quality of information generated by ChatGPT regarding dental implants and peri-implant phenotypes. A structured questionnaire on these topics was presented to the AI-based chatbot, and its responses were assessed by dental professionals using a modified Global Quality Scale (GQS) and the DISCERN tool. The study included 60 participants divided into three professional groups: oral and maxillofacial surgeons, periodontologists, and general dental practitioners. While no statistically significant differences were observed among the groups (p > 0.05), oral and maxillofacial surgeons consistently assigned lower DISCERN and GQS scores compared to other professionals. The findings of this study suggest that ChatGPT has the potential to serve as a supplementary tool for patient information in dental implant procedures. However, its responses may lack the depth and specificity required for clinical decision-making. Dental professionals should exercise caution when relying on artificial intelligence (AI) -generated content and guide patients in interpreting such information. Future research should explore the variability of AI responses, assess multiple chatbot platforms, and investigate their integration into dental clinical practice. | F15: Terzi, Mithat; Yavuz, Mustafa Cihan; Bicer, Tayyip; Buyuk, S Kutalmış | G15: 2025 | H15: Scientific reports | I15: 10.1038/s41598-025-94576-z | J15: 40108433.0 | K15: Journal article (original research) | L15: English | M15: Periodontology; Implant dentistry; Oral & maxillofacial surgery | N15: Amass BiomedCore (connector); DOAJ; Europe PMC; PubMed/MEDLINE; Semantic Scholar | O15: INCLUDE | P15: - | Q15: ChatGPT implants/peri-implant phenotype; GQS DISCERN; patient info potential | R15: INCLUDE | S15: - | T15: ChatGPT implant info; GQS and DISCERN by professionals; patient info | U15: =IF(AND(O15=R15,O15<>"UNSURE"),"Agree","Conflict/Unsure") -> Agree | Y15: 0.764 | Z15: 255 | AA15: No | AD15: INCLUDE | AE15: - | AF15: R1 = R2
A16: LLMDENT-0639 | B16: 15 | C16: calibration | D16: Integrating ChatGPT into Dental Education: Perceptions, Ethical Challenges, and Curriculum Development Implications | E16: Introduction: This preliminary investigation examined how the dental community views the incorporation of ChatGPT into the dental education curriculum and research. This research seeks to investigate how participants perceive, feel about, and prefer the potential use of ChatGPT to enhance teaching, learning, and research activities in dental education. Methods: A cross-sectional questionnaire was administered to 148 participants (37 staff and 111 students). The survey gathered data on the participants’ knowledge of ChatGPT, their views on its potential educational impact, and their preferences for integrating ChatGPT into the dental curriculum. Statistical analysis was performed to evaluate differences based on demographic and academic factors. Results: The study found that 47.3% of the participants demonstrated a good understanding of ChatGPT basics, with 52.7% recognizing its limitations in terms of education and research. The majority (66%) believed that ChatGPT would significantly influence dental education within two years. Despite positive attitudes towards its potential, 80.4% of the participants emphasized the need for careful management and control of ChatGPT. Less than 40% preferred personalized feedback from ChatGPT, with many participants highlighting the necessity for additional guidance and skill development to use the tool efficiently. Conclusion: The findings suggest that ChatGPT holds considerable promise in enhancing dental education. However, apprehensions … | F16: Sangeetha Narasimhan; Mohamed El-Kishawi; Sausan Al Kawas; Marwan Mansoor Mohammed; V. Kamath; S. Shetty | G16: 2026 | H16: Dubai Medical Journal | I16: 10.18502/dmj.v9is1.21025 | K16: Review (narrative) | L16: English (automatically detected) | M16: Preventive dentistry / dental public health; Dental education / exams | N16: DOAJ; Semantic Scholar | O16: EXCLUDE | P16: E3 | Q16: questionnaire on ChatGPT in dental education | R16: EXCLUDE | S16: E3 | T16: dental education perception questionnaire | U16: =IF(AND(O16=R16,O16<>"UNSURE"),"Agree","Conflict/Unsure") -> Agree | Y16: 0.018 | Z16: 2061 | AA16: No | AD16: EXCLUDE | AE16: E3 | AF16: R1 = R2
A17: LLMDENT-1964 | B17: 16 | C17: calibration | D17: Unlocking the Potentials of Large Language Models in Orthodontics: A Scoping Review. | E17: (1) Background: In recent years, large language models (LLMs) such as ChatGPT have gained significant attention in various fields, including dentistry. This scoping review aims to examine the current applications and explore potential uses of LLMs in the orthodontic domain, shedding light on how they might improve dental healthcare. (2) Methods: We carried out a comprehensive search in five electronic databases, namely PubMed, Scopus, Embase, ProQuest and Web of Science. Two authors independently screened articles and performed data extraction according to the eligibility criteria, following the PRISMA-ScR guideline. The main findings from the included articles were synthesized and analyzed in a narrative way. (3) Results: A total of 706 articles were searched, and 12 papers were eventually included. The applications of LLMs include improving diagnostic and treatment efficiency in orthodontics as well as enhancing communication with patients. (4) Conclusions: There is emerging research in countries worldwide on the use of LLMs in orthodontics, suggesting an upward trend in their acceptance within this field. However, the potential application of LLMs remains in its early stage, with a noticeable lack of extensive studies and tailored products to address specific clinical needs. | F17: Zheng, Jie; Ding, Xiaoqian; Pu, Jingya Jane; Chung, Sze Man; Ai, Qi Yong H; Hung, Kuo Feng; Shan, Zhiyi | G17: 2024 | H17: Bioengineering (Basel, Switzerland) | I17: 10.3390/bioengineering11111145 | J17: 39593805.0 | K17: Systematic / scoping review | L17: English | M17: Orthodontics; Oral & maxillofacial surgery | N17: Amass BiomedCore (connector); DOAJ; Europe PMC; PubMed/MEDLINE; Semantic Scholar | O17: EXCLUDE | P17: E5 | Q17: scoping review LLMs orthodontics | R17: EXCLUDE | S17: E5 | T17: scoping review LLMs orthodontics | U17: =IF(AND(O17=R17,O17<>"UNSURE"),"Agree","Conflict/Unsure") -> Agree | Y17: 0.037 | Z17: 2010 | AA17: No | AD17: EXCLUDE | AE17: E5 | AF17: R1 = R2
A18: LLMDENT-1346 | B18: 17 | C18: calibration | D18: Evaluating the quality and empathy of responses to patient questions on the Korean Academy of Periodontology's online question and answer section: a cross-sectional study comparing periodontists and an AI-powered chatbot. | E18: PURPOSE: This study aimed to evaluate and compare the responses of an artificial intelligence (AI)-powered chatbot and professional periodontists to patient queries in periodontology and implantology, using the Korean Academy of Periodontology's (KAP) online question and answer (Q&A) section. METHODS: In this comparative cross-sectional study, we analyzed 219 patient-submitted periodontal and implant knowledge questions from the KAP online Q&A section. A panel of 10 evaluators-5 periodontists and 5 laypersons-rated both the periodontist's and the AI chatbot's responses using standardized scales. We applied the t-test and Spearman correlation coefficients to compare response quality, empathy, consistency, and evaluator preferences. RESULTS: Ten evaluators judged the AI chatbot's responses to be significantly superior in quality and empathy compared to periodontist replies. A higher proportion of periodontist responses fell below acceptable quality ("very poor" or "poor") than chatbot responses (28.7% vs. 15.0%; P<0.001), and more chatbot replies were rated "empathetic" or "very empathetic" (62.5% vs. 42.8%; P<0.001). Overall response consistency was deemed satisfactory at 64.2%, with no significant difference in consistency or preference between periodontist and lay evaluators. CONCLUSIONS: AI-powered chatbots can deliver more accurate and empathetic answers than human periodontists, suggesting their potential role as consultation assistants merits further investigation. The h… | F18: Lee, Jae-Hong; Oh, So-Hae; Schwendicke, Falk; Chaurasia, Akhilanand; Kim, Young-Taek | G18: 2025 | H18: Journal of periodontal & implant science | I18: 10.5051/jpis.2402220111 | J18: 40501075.0 | K18: Journal article (original research) | L18: English | M18: Periodontology; Implant dentistry | N18: Crossref; Europe PMC; PubMed/MEDLINE; Semantic Scholar | O18: INCLUDE | P18: - | Q18: patient questions KAP Q&A; chatbot vs periodontists; quality empathy | R18: INCLUDE | S18: - | T18: KAP patient Q&A periodontology; chatbot vs periodontists; quality rated | U18: =IF(AND(O18=R18,O18<>"UNSURE"),"Agree","Conflict/Unsure") -> Agree | Y18: 0.764 | Z18: 256 | AA18: No | AD18: INCLUDE | AE18: - | AF18: R1 = R2
A19: LLMDENT-1364 | B19: 18 | C19: calibration | D19: Accuracy and reliability of Manus, ChatGPT, and Claude in case-based dental diagnosis. | E19: INTRODUCTION: Artificial intelligence (AI), particularly large language models (LLMs), is transforming healthcare education and clinical decision-making. While models like ChatGPT and Claude have demonstrated utility in medical contexts, their performance in dental diagnostics remains underexplored; additionally, the potential of emerging platforms, like Manus, is yet to be evaluated. OBJECTIVE: To compare the diagnostic accuracy and consistency of the ChatGPT, Claude, and Manus-using authentic, case-based dental scenarios. METHODS: A set of 117 multiple-choice questions based on validated clinical dental vignettes spanning various specialities was administered to each model under standardised conditions at two separate time points. Responses were scored against expert-validated answer keys. Inter-rater reliability was assessed using Cohen's kappa, and statistical comparisons were made using the chi-square, McNemar, and t-tests. RESULTS: Claude and Manus consistently outperformed ChatGPT across both testing phases. In the second round, Claude and Manus achieved a diagnostic accuracy of 92.3%, compared to ChatGPT's 76.9%. Claude and Manus also demonstrated higher intra-model consistency (Cohen's kappa = 0.714 and 0.782, respectively) than ChatGPT (kappa = 0.560). Although the numerical trends favoured Claude and Manus, pairwise differences in accuracy did not reach statistical significance. CONCLUSION: Claude and Manus demonstrated numerically higher diagnostic performance and… | F19: Madfa, Ahmed A; Alshammari, Abdullah F; Anazi, Bassam A; Alenezi, Yousef E; Alkurdi, Khlood A | G19: 2025 | H19: Frontiers in oral health | I19: 10.3389/froh.2025.1686090 | J19: 41584961.0 | K19: Journal article (original research) | L19: English | M19: Dental education / exams; General dentistry / cross-specialty | N19: Amass BiomedCore (connector); Crossref; DOAJ; Europe PMC; PubMed/MEDLINE; Semantic Scholar | O19: EXCLUDE | P19: E3 | Q19: MCQ clinical vignettes diagnostic accuracy | R19: EXCLUDE | S19: E3 | T19: MCQ clinical vignettes diagnostic accuracy | U19: =IF(AND(O19=R19,O19<>"UNSURE"),"Agree","Conflict/Unsure") -> Agree | Y19: 0.318 | Z19: 816 | AA19: No | AD19: EXCLUDE | AE19: E3 | AF19: R1 = R2
A20: LLMDENT-0239 | B20: 19 | C20: calibration | D20: Comment on "Diagnostic Performance of Multimodal Large Language Models in the Analysis of Oral Pathology". | E20: The data that support the findings of this study are available from the corresponding author, Hinpetch Daungsupawong, upon reasonable request. | F20: Daungsupawong, Hinpetch; Wiwanitkit, Viroj | G20: 2026 | H20: Oral diseases | I20: 10.1111/odi.70055 | J20: 40760938.0 | K20: Letter / comment / editorial | L20: English | M20: Oral medicine / oral pathology | N20: Europe PMC; PubMed/MEDLINE; Semantic Scholar | O20: EXCLUDE | P20: E3 | Q20: comment on multimodal LLM oral pathology diagnosis | R20: EXCLUDE | S20: E3 | T20: comment on multimodal oral pathology diagnosis; also letter | U20: =IF(AND(O20=R20,O20<>"UNSURE"),"Agree","Conflict/Unsure") -> Agree | Y20: -0.037 | Z20: 2134 | AA20: No | AD20: EXCLUDE | AE20: E3 | AF20: R1 = R2
A21: LLMDENT-0827 | B21: 20 | C21: calibration | D21: Preliminary Evaluation of Large Language Models in Kennedy Classification and Removable Partial Denture Planning: An In Silico Study. | E21: BACKGROUND This study evaluated text-based large language models for Kennedy classification and removable partial denture planning in partially edentulous cases, where comparative evidence on accuracy remains limited. MATERIAL AND METHODS Twenty-six partially edentulous cases, defined according to the Federation Dentaire Internationale tooth numbering system and classified as Kennedy Classes I to IV, were included. Case scenarios were constructed by an experienced prosthodontist. Questions were independently submitted to 4 large language models without prior training or prompting: ChatGPT-5.2, Claude Sonnet 4.6, Gemini 3 Flash, and Perplexity. Responses were evaluated by 2 independent prosthodontists (different from the case developer) - blinded to the identity of each model - using predefined criteria for Kennedy classification accuracy and prosthetic planning consistency. Statistical analyses included intergroup comparisons and effect size estimation. RESULTS Statistically significant differences were identified among the models in both tasks (P<0.001). For Kennedy classification, the effect size was moderate (Kendall's W=0.402). Gemini 3 Flash achieved the highest mean score, followed by ChatGPT-5.2, Perplexity, and Claude Sonnet 4.6. Similarly, significant differences were observed in removable partial denture planning performance (Kendall's W=0.424); Gemini 3 Flash scored significantly higher than the other models (P≤0.001). CONCLUSIONS Large language models showed varia… | F21: Sümer Ekin, Ebru; Değer, Yalçın; Dündar Yilmaz, Berivan; Yildiz, İsmail | G21: 2026 | H21: Medical science monitor : international medical journal of experimental and clinical research | I21: 10.12659/msm.953353 | J21: 42093138.0 | K21: Journal article (original research) | L21: English | M21: Prosthodontics | N21: Europe PMC; PubMed/MEDLINE; Semantic Scholar | O21: EXCLUDE | P21: E3 | Q21: Kennedy classification and RPD planning for clinicians | R21: EXCLUDE | S21: E3 | T21: Kennedy classification and RPD planning cases for clinicians | U21: =IF(AND(O21=R21,O21<>"UNSURE"),"Agree","Conflict/Unsure") -> Agree | Y21: 0.447 | Z21: 541 | AA21: No | AD21: EXCLUDE | AE21: E3 | AF21: R1 = R2
A22: LLMDENT-0367 | B22: 21 | C22: calibration | D22: Psychological Inclinations and Practical Utility of ChatGPT Among Undergraduate Dental Students at a Dental School in Karachi: A Cross-Sectional Observational Study. | E22: ABSTRACT Objectives This study aims to explore the correlation of psychological domains and behavioural engagement with ChatGPT among undergraduate dental students. Material and Methods A cross‐sectional study was conducted using a self‐administered questionnaire (supporting material) distributed to 130 undergraduate dental students of a dental school in Karachi, Pakistan. The questionnaire assessed the frequency and purpose of ChatGPT usage across academic domains and specific learning contexts. It also evaluated students’ attitudes, perceptions, and behaviors using a Likert scale. Descriptive statistics were used for analysis, while Spearman's correlation tests were applied to examine subgroup differences and relationships between attitudes and behaviors. Results Most participants reported learning about ChatGPT through peers or friends (n = 53) and social media (n = 38). The mean composite scores for the psychological domains [Perception(3.27), behaviour (3.21) and Attitude (3.19)] indicate a generally neutral‐to‐moderately positive inclination toward ChatGPT. The primary area of usage was basic dental sciences (n = 73). A strong positive correlation was observed between trust in ChatGPT for dental explanations and behavioral engagement (rs = 0.86, 95% CI [0.88, 0.95], p = 0.003, Holm–Bonferroni adjusted p = 0.006), while doubts regarding its accuracy were negatively correlated with engagement (rs = −0.91, 95% CI [−0.97, −0.76], p = 0.002, adjusted p = 0.006). Students who… | F22: Hanif, Ayesha; Gul, Amna; Maqsood, Afsheen; Naeem, Marium; Shahid, Rumaisa; Abbasi, Maria Shakoor; Ahmed, Naseer; Heboyan, Artak | G22: 2026 | H22: Health science reports | I22: 10.1002/hsr2.71808 | J22: 41694212.0 | K22: Journal article (original research) | L22: English | M22: Dental education / exams; General dentistry / cross-specialty | N22: Crossref; DOAJ; Europe PMC; PubMed/MEDLINE; Semantic Scholar | O22: EXCLUDE | P22: E3 | Q22: dental student survey on ChatGPT use | R22: EXCLUDE | S22: E3 | T22: dental student ChatGPT usage/attitude questionnaire | U22: =IF(AND(O22=R22,O22<>"UNSURE"),"Agree","Conflict/Unsure") -> Agree | Y22: 0.184 | Z22: 1330 | AA22: No | AD22: EXCLUDE | AE22: E3 | AF22: R1 = R2
A23: LLMDENT-0417 | B23: 22 | C23: calibration | D23: Can Large Language Models Support Endodontic Decision-Making? Accuracy and Consistency of ChatGPT and Gemini in Deep Caries and Pulp Exposure | E23: Background: This study evaluated the accuracy and consistency of responses generated by 2 large language models (LLMs), ChatGPT and Gemini, regarding the management of deep carious lesions and pulp exposure in endodontics. Methods: Fifty dichotomous (Yes/No) questions were developed based on the position statement of the European Society of Endodontology and distributed across 5 categories: Diagnosis and Classification, Caries Management, Pulp Exposure Management, Materials and Techniques, and Follow-up and Prognosis. Questions were presented to ChatGPT-4o and Gemini (Flash 2.5) on 3 occasions, 1 week apart. A total of 300 responses were collected and compared with reference answers. Accuracy was measured as the proportion of correct responses, while consistency was assessed using Fleiss’ Kappa across time points. Statistical analyses included Cochran’s Q and McNemar’s test, with significance set at P < .05. Results: ChatGPT achieved an overall accuracy of 76.7%, while Gemini achieved 86.0%, a statistically significant difference favoring Gemini (P=.034). By categories, Gemini showed superior accuracy in Caries Management and Pulp Exposure Management (96.7%), while ChatGPT performed best in Diagnosis and Classification (93.3%). Substantial consistency was observed for both models (Fleiss’ Kappa=0.627 for ChatGPT; 0.723 for Gemini). Gemini’s accuracy varied significantly across weeks (P=.015), whereas ChatGPT’s remained stable (P=.670). Conclusion: Both LLM-based chatbots demo… | F23: Işık, Vasfiye; Şişmanoğlu, Soner; Baybora Kayahan, Mehmet | G23: 2026 | H23: Essentials of Dentistry | I23: 10.5152/essentdent.2026.0113 | K23: Journal article (original research) | L23: English (automatically detected) | M23: Endodontics; Restorative dentistry / cariology | N23: Crossref; DOAJ; Semantic Scholar | O23: EXCLUDE | P23: E3 | Q23: yes/no questions on ESE position statement; clinician decision support | R23: EXCLUDE | S23: E3 | T23: ESE position statement yes/no questions; clinical decision-making for dentists | U23: =IF(AND(O23=R23,O23<>"UNSURE"),"Agree","Conflict/Unsure") -> Agree | Y23: 0.448 | Z23: 539 | AA23: No | AD23: EXCLUDE | AE23: E3 | AF23: R1 = R2
A24: LLMDENT-1439 | B24: 23 | C24: calibration | D24: Odontozap: um chatbot para orientar o atendimento de urgências odontológicas no contexto do SUS | E24: Introdução: Muitos pacientes têm dificuldade em identificar se suas queixas odontológicas exigem atendimento de urgência; o que pode impactar negativamente a jornada de cuidado no SUS. Este trabalho apresenta o desenvolvimento do Odontozap; chatbot criado para orientar pacientes em busca por atendimento odontológico de urgência. A pesquisa adota uma abordagem centrada no usuário envolvendo dentistas e pacientes; com etapas de validação; prototipação e realização de testes de usabilidade. O objetivo é explorar como uma tecnologia interativa pode qualificar e facilitar o acesso a serviços de saúde no contexto do SUS. | F24: L. M. A. Pinheiro; F. Germano; M. D. Gomes; I. Sabóia | G24: 2025 | H24: Anais Estendidos do XXIV Simpósio Brasileiro sobre Fatores Humanos em Sistemas Computacionais (IHC 2025) | I24: 10.5753/ihc_estendido.2025.13252 | K24: Not specified | L24: Portuguese (automatically detected) | M24: General dentistry / cross-specialty | N24: Semantic Scholar | O24: EXCLUDE | P24: E2 | Q24: custom urgent-care chatbot prototype; usability; no general LLM | R24: EXCLUDE | S24: E2 | T24: Odontozap urgency triage chatbot; no general-purpose LLM evident; usability | U24: =IF(AND(O24=R24,O24<>"UNSURE"),"Agree","Conflict/Unsure") -> Agree | Y24: 0.197 | Z24: 1268 | AA24: No | AD24: EXCLUDE | AE24: E2 | AF24: R1 = R2
A25: LLMDENT-0599 | B25: 24 | C25: calibration | D25: Challenges and Limitations of Multimodal Large Language Models in Interpreting Pediatric Panoramic Radiographs. | E25: ABSTRACT Background Multimodal large language models (LLMs) have potential for medical image analysis, yet their reliability for pediatric panoramic radiographs remains uncertain. Aim This study evaluated two multimodal LLMs (OpenAI o1, Claude 3.5 Sonnet) for detecting and counting teeth (including tooth germs) on pediatric panoramic radiographs. Design Eighty‐seven pediatric panoramic radiographs from an open‐source data set were analyzed. Two pediatric dentists annotated the presence or absence of each potential tooth position. Each image was processed five times by the LLMs using identical prompts, and the results were compared with the expert annotations. Standard performance metrics and Fleiss' kappa were calculated. Results Detailed examination revealed that subtle developmental stages and minor tooth loss were consistently misidentified. Claude 3.5 Sonnet had higher sensitivity but significantly lower specificity (29.8% ± 21.5%), resulting in many false positives. OpenAI o1 demonstrated superior specificity compared to Claude 3.5 Sonnet, but still failed to correctly detect subtle defects in certain mixed dentition cases. Both models showed large variability in repeated runs. Conclusion Both LLMs failed to achieve clinically acceptable performance and cannot reliably identify nuanced discrepancies critical for pediatric dentistry. Further refinements and consistency improvements are essential before routine clinical use. | F25: Mine, Yuichi; Iwamoto, Yuko; Okazaki, Shota; Nishimura, Taku; Tabata, Eimi; Takeda, Saori; Peng, Tzu-Yu; Nomura, Ryota; Kakimoto, Naoya; Murayama, Takeshi | G25: 2026 | H25: International journal of paediatric dentistry | I25: 10.1111/ipd.70029 | J25: 40958411.0 | K25: Journal article (original research) | L25: English | M25: Pediatric dentistry; Oral & maxillofacial radiology | N25: Crossref; Europe PMC; PubMed/MEDLINE; Semantic Scholar | O25: EXCLUDE | P25: E3 | Q25: multimodal LLM pediatric panoramic radiograph interpretation | R25: EXCLUDE | S25: E3 | T25: multimodal LLMs on pediatric panoramic radiographs; image interpretation | U25: =IF(AND(O25=R25,O25<>"UNSURE"),"Agree","Conflict/Unsure") -> Agree | Y25: 0.173 | Z25: 1380 | AA25: No | AD25: EXCLUDE | AE25: E3 | AF25: R1 = R2
A26: LLMDENT-1255 | B26: 25 | C26: calibration | D26: DentalBench: Benchmarking and Advancing LLMs Capability for Bilingual Dentistry Understanding | E26: Recent advances in large language models (LLMs) and medical LLMs (Med-LLMs) have demonstrated strong performance on general medical benchmarks. However, their capabilities in specialized medical fields, such as dentistry which require deeper domain-specific knowledge, remain underexplored due to the lack of targeted evaluation resources. In this paper, we introduce DentalBench, the first comprehensive bilingual benchmark designed to evaluate and advance LLMs in the dental domain. DentalBench consists of two main components: DentalQA, an English-Chinese question-answering (QA) benchmark with 36,597 questions spanning 4 tasks and 16 dental subfields; and DentalCorpus, a large-scale, high-quality corpus with 337.35 million tokens curated for dental domain adaptation, supporting both supervised fine-tuning (SFT) and retrieval-augmented generation (RAG). We evaluate 14 LLMs, covering proprietary, open-source, and medical-specific models, and reveal significant performance gaps across task types and languages. Further experiments with Qwen-2.5-3B demonstrate that domain adaptation substantially improves model performance, particularly on knowledge-intensive and terminology-focused tasks, and highlight the importance of domain-specific benchmarks for developing trustworthy and effective LLMs tailored to healthcare applications. | F26: Hengchuan Zhu; Yihua Xu; Yichen Li; Zi-Jie Meng; Zuo-Zhu Liu | G26: 2025 | H26: ArXiv | I26: 10.48550/arxiv.2508.20416 | K26: Preprint | L26: English (automatically detected) | M26: General dentistry / cross-specialty | N26: Semantic Scholar; arXiv | O26: EXCLUDE | P26: E3 | Q26: DentalBench professional QA benchmark; domain adaptation | R26: EXCLUDE | S26: E3 | T26: DentalBench knowledge QA benchmark; domain adaptation; not patient-facing | U26: =IF(AND(O26=R26,O26<>"UNSURE"),"Agree","Conflict/Unsure") -> Agree | Y26: 0.12 | Z26: 1660 | AA26: No | AD26: EXCLUDE | AE26: E3 | AF26: R1 = R2
A27: LLMDENT-2153 | B27: 26 | C27: calibration | D27: Frictional Resistance of Non Coated and Epoxy Coated Superelastic NiTi Wires used for Aligning in Three Types of Brackets | E27: Introduction: Coated archwires are preferred in combination with aesthetic orthodontic brackets by orthodontists over non metallic aesthetic archwires. Studies evaluating the frictional properties of epoxy coated round superelastic Nickel Titanium (NiTi) archwires are limited to stainless steel brackets. Aim: To evaluate and compare the frictional resistance of an epoxy coated 0.016*" superelastic NiTi archwire in stainless steel, composite and ceramic brackets and to compare it with the frictional resistance generated by non coated 0.016*" superelastic NiTi archwire in same brackets. Materials and Methods: An in-vitro experimental study was conducted in the Department of Orthodontics at SRM Dental College, Ramapuram Chennai, Tamil Nadu, India, from January to February 2020. Frictional resistance of 30 epoxy coated aesthetic 0.016*" upper superelastic NiTi wires (G4™ Nickel Titanium, 0.016*, Upper Trueform™ I, Tooth-Colored) and 30 conventional 0.016*" upper superelastic NiTi wires (G4™ Nickel Titanium, 0.016*, Upper Trueform™) from G&H® orthodontics while sliding across three different types of brackets were evaluated. Twenty stainless steel (Gemini® 3M unitek, Monrovia, California), 20 composite (FLI® RMO, Denver, Colo.), and 20 gemini clear ceramic (Gemini clear ® 3M unitek, Monrovia, California) 0.022×0.028" Slot Roth prescription maxillary first premolar brackets were used. The brackets and archwires were divided into six groups of different bracket and archwire combinat… | F27: Monisha C Ravishankar; Sangeetha Duraisamy; Krishnaraj Rajaram; R. Kannan; N. Sivakumar | G27: 2022 | H27: JOURNAL OF CLINICAL AND DIAGNOSTIC RESEARCH | I27: 10.7860/jcdr/2022/55490.16414 | K27: Not specified | L27: English (automatically detected) | M27: Orthodontics; Esthetic dentistry; Dental pharmacology / anesthesia | N27: DOAJ; Semantic Scholar | O27: EXCLUDE | P27: E2 | Q27: orthodontic wire friction in vitro; no LLM | R27: EXCLUDE | S27: E2 | T27: in-vitro orthodontic archwire friction; no LLM | U27: =IF(AND(O27=R27,O27<>"UNSURE"),"Agree","Conflict/Unsure") -> Agree | Y27: 0.233 | Z27: 1096 | AA27: No | AD27: EXCLUDE | AE27: E2 | AF27: R1 = R2
A28: LLMDENT-0064 | B28: 27 | C28: calibration | D28: Reliability of three artificial intelligence chatbots in responding to patient questions about surgical endodontics: An observational study | E28: Artificial intelligence (AI) chatbots are increasingly used by the public to obtain medical and dental information, including inquiries related to endodontic surgery. Evaluating the accuracy of these platforms is essential to ensure reliable patient education. This study aimed to assess and compare the reliability of three advanced AI chatbot platforms – ChatGPT-5, DeepSeek, and Grok in responding to patient-style questions related to surgical endodontic treatment. A set of 16 patient-centered questions covering four domains (indications, procedure, postoperative care, and complications) was presented to each AI platform. Responses were independently evaluated by two board-certified specialists using a 5-point Likert-type scale (1 = strongly disagree to 5 = strongly agree) reflecting alignment with evidence-based surgical endodontic standards. Descriptive statistics were used to summarize the distribution of ratings, and a Chi-square test was prespecified for potential comparative analysis. All platforms demonstrated consistently high reliability. ChatGPT-5 and DeepSeek each received 15 ratings of 5 and 1 rating of 4, while Grok received 14 ratings of 5 and 2 ratings of 4. No responses from any platform were rated as neutral or negative. Because all responses were rated “agree” or “strongly agree,” no inferential statistical testing was performed. All tested AI chatbot platforms performed comparably in delivering clinically relevant and accurate responses to patient-style end… | F28: W. Almutairi | G28: 2026 | H28: Saudi Endodontic Journal | I28: 10.4103/sej.sej_256_25 | K28: Journal article (original research) | L28: English (automatically detected) | M28: Endodontics | N28: Consensus (connector); Semantic Scholar | O28: INCLUDE | P28: - | Q28: patient-style surgical endodontics questions; GPT-5 DeepSeek Grok; specialist Likert | R28: INCLUDE | S28: - | T28: patient-style surgical endodontic questions; ChatGPT-5 DeepSeek Grok; specialist Likert | U28: =IF(AND(O28=R28,O28<>"UNSURE"),"Agree","Conflict/Unsure") -> Agree | Y28: 0.866 | Z28: 182 | AA28: No | AD28: INCLUDE | AE28: - | AF28: R1 = R2
A29: LLMDENT-1655 | B29: 28 | C29: calibration | D29: Evaluation of the readability, quality, and accuracy of AI chatbot responses to questions about deleterious oral habits. | E29: Abstract Background Artificial intelligence (AI)-based chatbots are increasingly used by parents as convenient and fast-access sources of information on health-related topics. This study aimed to assess the readability, accuracy and overall quality of responses provided by ChatGPT-4o, Google Gemini and Microsoft Copilot to questions concerning deleterious oral habits in children. Methods A total of 43 questions, derived from real-life discussions on the Reddit platform, were revised for clarity and demographic diversity. These were classified into seven categories based on specific types of deleterious oral habits, including thumb sucking, bruxism, pacifier use, bruxism, tongue thrusting, lip sucking, nail biting, and mouth breathing. Responses from each AI chatbot were evaluated using multiple evaluation tools including Flesch Reading Ease (FRE), Flesch-Kincaid Grade Level (FKGL), the modified DISCERN tool (mDISCERN), Global Quality Score (GQS), and misinformation scoring system. Statistical analyses were performed using the Kruskal–Wallis test followed by Dunn’s post hoc test for non-normally distributed variables, and one-way ANOVA with Tukey’s post hoc test for normally distributed variables (p < .05). Results ChatGPT-4o generated responses with significantly lower readability and higher textual complexity compared to Gemini and Copilot, as reflected by its lower FRE (p = .0022) and higher FKGL (p = .0062) scores. ChatGPT-4o had 76.74% of its responses rated as excellent … | F29: Özdemir, Ömer Tarık; Kavan, Melis Yazır; Güven, Yeliz | G29: 2025 | H29: BMC oral health | I29: 10.1186/s12903-025-07298-z | J29: 41272704.0 | K29: Journal article (original research) | L29: English | M29: Pediatric dentistry; TMD / orofacial pain; Preventive dentistry / dental public health | N29: Amass BiomedCore (connector); Consensus (connector); DOAJ; Europe PMC; PubMed/MEDLINE; Semantic Scholar | O29: INCLUDE | P29: - | Q29: parent Reddit questions oral habits; GQS mDISCERN misinformation; 3 chatbots | R29: INCLUDE | S29: - | T29: parent Reddit questions on oral habits; GQS mDISCERN misinformation | U29: =IF(AND(O29=R29,O29<>"UNSURE"),"Agree","Conflict/Unsure") -> Agree | Y29: 1.121 | Z29: 29 | AA29: No | AD29: INCLUDE | AE29: - | AF29: R1 = R2
A30: LLMDENT-0920 | B30: 29 | C30: calibration | D30: Exploring the use of large language models for self-learning in preventive dentistry and their associations with academic performance: a cross-sectional pilot study among dental students. | E30: BACKGROUND: Large language models (LLMs) are being gradually integrated into dental education, but more attention was paid in perspective of educators rather than students. Evidence regarding how students employ them for self-learning in Preventive Dentistry, and whether specific usage patterns are related to academic performance, remains scarce. This study examined dental students' self-perceived LLM knowledge, attitudes, and behaviors; evaluated perceived usefulness across Preventive Dentistry modules; and explored associations between LLM usage (frequency, type, motivation) and academic performance. METHODS: This cross-sectional pilot study recruited all third-year dental undergraduates enrolled in a Preventive Dentistry course at a university in eastern China. A total of 117 students provided valid responses and completed final examination. Academic performance was assessed using final examination scores as a continuous outcome variable. Linear regression analysis was performed to examine associations between LLM usage and examination scores. The data were analyzed using SPSS 22.0, and the level of significance was set at 0.05. RESULTS: LLM use was reported by all participants, with eighty-four students (71.8%) considering themselves as proficient users. For self-learning in Preventive Dentistry, 49.6% of participants reported using LLMs one to three times per month and DeepSeek (99.1%) was most popular. Students perceived LLMs as more helpful for theoretical learning tha… | F30: Yang, Jiayi; Li, Mingming; Wang, Shuhua; Shi, Zhuojin; Fang, Jinhua; Zheng, Pei; Wu, Zhiwu | G30: 2026 | H30: BMC oral health | I30: 10.1186/s12903-026-09345-9 | J30: 42472798.0 | K30: Journal article (original research) | L30: English | M30: Preventive dentistry / dental public health; Dental education / exams | N30: Crossref; Europe PMC; PubMed/MEDLINE; Semantic Scholar | O30: EXCLUDE | P30: E3 | Q30: dental student LLM self-learning survey | R30: EXCLUDE | S30: E3 | T30: dental student LLM self-learning survey | U30: =IF(AND(O30=R30,O30<>"UNSURE"),"Agree","Conflict/Unsure") -> Agree | Y30: 0.17 | Z30: 1397 | AA30: No | AD30: EXCLUDE | AE30: E3 | AF30: R1 = R2
A31: LLMDENT-1156 | B31: 30 | C31: calibration | D31: Comment on "Image-Based Diagnostic Performance of LLMs vs CNNs for Oral Lichen Planus". | F31: Daungsupawong, Hinpetch; Wiwanitkit, Viroj | G31: 2025 | H31: International dental journal | I31: 10.1016/j.identj.2025.100888 | J31: 40664572.0 | K31: Letter / comment / editorial | L31: English | M31: Oral medicine / oral pathology | N31: DOAJ; Europe PMC; PubMed/MEDLINE; Semantic Scholar | O31: EXCLUDE | P31: E3 | Q31: comment on image-based LLM diagnosis oral lichen planus | R31: EXCLUDE | S31: E3 | T31: comment on image-based oral lichen planus diagnosis | U31: =IF(AND(O31=R31,O31<>"UNSURE"),"Agree","Conflict/Unsure") -> Agree | Y31: 0.026 | Z31: 2041 | AA31: No | AD31: EXCLUDE | AE31: E3 | AF31: R1 = R2
A32: LLMDENT-1376 | B32: 31 | C32: calibration | D32: Comparing dentist and chatbot answers to dental questions for quality and empathy. | E32: BACKGROUND: Integration of large language models (LLMs) into health care, particularly in patient communication, is a growing trend. This study evaluated the effectiveness of LLM chatbots in addressing dental patient queries compared with responses from human dentists on a public online forum. METHODS: In January 2024, 20 patient questions and responses were randomly sampled from Reddit's dental advice community. We assessed the quality and empathy of ChatGPT-generated responses (Version GPT-3.5, OpenAI) by 9 blinded dentists. The dentists were selected from a dental faculty pool familiar with reading and assessing written communication. The evaluators rated the information quality of the responses on a Likert scale (very poor, 1; poor, 2; acceptable, 3; good, 4; very good, 5) and empathy (not empathetic, 1; slightly empathetic, 2; moderately empathetic, 3; empathetic, 4; very empathetic, 5). Subsequently, they selected the best response (dentist or artificial intelligence). Nine blinded dentists rated 20 responses to the online inquiries, providing 180 potential responses. RESULTS: The results indicated that the LLM chatbots' responses were rated as higher quality and exhibited higher levels of empathy than human responses. Among 179 responses (1 was missing) to the question about whether the response was better from ChatGPT or the dentist, 167 (93.3%) responses indicated ChatGPT and 12 (6.7%) indicated dentist (P < .001). CONCLUSIONS: Although subjective variations in asses… | F32: Maruska, Erin E; Elgreatly, Amira; Madaio, William; Razoky, Klud; Bay, Curt; Mahrous, Ahmed | G32: 2025 | H32: JADA foundational science | I32: 10.1016/j.jfscie.2025.100044 | J32: 42238112.0 | K32: Journal article (original research) | L32: English | M32: Preventive dentistry / dental public health | N32: Consensus (connector); Crossref; Europe PMC; PubMed/MEDLINE; Semantic Scholar | O32: INCLUDE | P32: - | Q32: Reddit patient questions; GPT-3.5 vs dentists; quality and empathy | R32: INCLUDE | S32: - | T32: Reddit dental patient questions; ChatGPT vs dentists; quality empathy | U32: =IF(AND(O32=R32,O32<>"UNSURE"),"Agree","Conflict/Unsure") -> Agree | Y32: 0.87 | Z32: 178 | AA32: No | AD32: INCLUDE | AE32: - | AF32: R1 = R2
A33: LLMDENT-1989 | B33: 32 | C33: calibration | D33: Can ChatGPT be used in oral and maxillofacial surgery? | E33: OBJECTIVE: The aim of this study is to assess the usability of the information generated by ChatGPT in oral and maxillofacial surgery. This assessment will have two components: Firstly, to measure the quality of patient information provided, and secondly, to measure the quality of educational information in this field. MATERIALS AND METHODS: Commonly asked questions by patients about oral and maxillofacial surgical procedures and technical questions for training purposes were selected to be posed to ChatGPT. The questions were divided into two categories, consisting of 60 Patient Questions and 60 Technical Questions. The specific topics covered were Impacted Teeth, Dental Implants, Temporomandibular Joint Diseases, and Orthognathic Surgery. ChatGPT provided responses to these questions on February 23, 2023. The answers were evaluated by oral and maxillofacial surgeons using a modified global quality scale. RESULTS: The study involved 33 participating surgeons. The mean score for the answers to the Patient Questions was 4.62±0.78, while the mean score for answers to the Technical Questions was 3.1 ± 1.49. The difference in scores between the two question categories was found to be statistically significant (P 0.05). CONCLUSIONS: ChatGPT has significant potential as a tool for patient information in oral and maxillofacial surgery. However, its use in training may not be completely safe at present. Surgeons should exercise caution when using ChatGPT and consider it as a suppleme… | F33: Balel, Yunus | G33: 2023 | H33: Journal of stomatology, oral and maxillofacial surgery | I33: 10.1016/j.jormas.2023.101471 | J33: 37061037.0 | K33: Journal article (original research) | L33: English | M33: Orthodontics; Implant dentistry; Oral & maxillofacial surgery; TMD / orofacial pain | N33: Amass BiomedCore (connector); Consensus (connector); Crossref; Europe PMC; PubMed/MEDLINE; Semantic Scholar | O33: INCLUDE | P33: - | Q33: OMFS patient questions plus technical; ChatGPT; modified GQS by surgeons | R33: INCLUDE | S33: - | T33: OMFS patient and technical questions; ChatGPT; modified GQS by surgeons | U33: =IF(AND(O33=R33,O33<>"UNSURE"),"Agree","Conflict/Unsure") -> Agree | Y33: 0.99 | Z33: 91 | AA33: No | AD33: INCLUDE | AE33: - | AF33: R1 = R2
A34: LLMDENT-1813 | B34: 33 | C34: calibration | D34: Dr. ChatGPT: Utilizing Artificial Intelligence in Surgical Education. | E34: OBJECTIVE: This study sought to explore the unexamined capabilities of ChatGPT in describing the surgical steps of a specialized operation, the Fisher cleft lip repair. DESIGN: A chat log within ChatGPT was created to generate the procedural steps of a cleft lip repair utilizing the Fisher technique. A board certified craniomaxillofacial (CMF) surgeon then wrote the Fisher repair in his own words blinded to the ChatGPT response. Using both responses, a voluntary survey questionnaire was distributed to residents of plastic and reconstructive surgery (PRS), general surgery (GS), internal medicine (IM), and medical students at our institution in a blinded study. SETTING: Authors collected information from residents (PRS, GS, IM) and medical students at one institution. MAIN OUTCOME MEASURES: Primary outcome measures included understanding, preference, and author identification of the procedural prompts. RESULTS: Results show PRS residents were able to detect more inaccuracies of the ChatGPT response as well as prefer the CMF surgeon's prompt in performing the surgery. Residents with less expertise in the procedure not only failed to detect who wrote what procedure, but preferred the ChatGPT response in explaining the concept and chose it to perform the surgery. CONCLUSIONS: In applications to surgical education, ChatGPT was found to be effective in generating easy to understand procedural steps that can be followed by medical personnel of all specialties. However, it does not ha… | F34: Lebhar, Michael S; Velazquez, Alexander; Goza, Shelby; Hoppe, Ian C | G34: 2024 | H34: The Cleft palate-craniofacial journal : official publication of the American Cleft Palate-Craniofacial Association | I34: 10.1177/10556656231193966 | J34: 37545428.0 | K34: Journal article (original research) | L34: English | M34: Oral & maxillofacial surgery; Dental education / exams | N34: Europe PMC; PubMed/MEDLINE; Semantic Scholar | O34: EXCLUDE | P34: E3 | Q34: cleft lip repair surgical steps for surgical education | R34: EXCLUDE | S34: E3 | T34: cleft lip repair surgical steps for surgical education | U34: =IF(AND(O34=R34,O34<>"UNSURE"),"Agree","Conflict/Unsure") -> Agree | Y34: 0.275 | Z34: 942 | AA34: No | AD34: EXCLUDE | AE34: E3 | AF34: R1 = R2
A35: LLMDENT-2116 | B35: 34 | C35: calibration | D35: Conversational Agents to Support Couple Therapy | E35: There is a growing rate of marriages and relationship dissolution as couples surrender efforts to reconcile. Couple therapy provides psychotherapeutic solutions for this problem. However, it is not easily accessible due to scheduling difficulties or cost. Conversational agents (CAs) could provide more scalable access to couple therapy. This study investigates the suitability of conversational agents for individual therapy for couple problems. Couple Therapy Chatbot is a Wizard-of-Oz intervention using cognitive-behavioural couple therapy (CBCT) with individuals via an instant messaging platform. 12 participants trialled Couple Therapy Chatbot via single-session therapy. A qualitative self-reported questionnaire provided suitability insights. Thematic analysis revealed that while some participants appreciate deep and constructive responses and human-like empathy, others dislike generic and impersonal responses. Using CAs for couple problems appears to be a suitable application and may assist in mitigating relationship dissolution. Future work can assess efficacy using automated CA solutions against larger and more selective samples. | F35: Berkan Yuksel; A. B. Kocaballi | G35: 2022 | H35: Proceedings of the 34th Australian Conference on Human-Computer Interaction | I35: 10.1145/3572921.3572922 | K35: Book / book chapter | L35: English (automatically detected) | M35: Oral & maxillofacial radiology | N35: Semantic Scholar | O35: EXCLUDE | P35: E1 | Q35: couple therapy conversational agent; not dental | R35: EXCLUDE | S35: E1 | T35: couple therapy conversational agent; not dental | U35: =IF(AND(O35=R35,O35<>"UNSURE"),"Agree","Conflict/Unsure") -> Agree | Y35: 0.225 | Z35: 1147 | AA35: No | AD35: EXCLUDE | AE35: E1 | AF35: R1 = R2
A36: LLMDENT-1650 | B36: 35 | C36: calibration | D36: ChatGPT and oral cancer: a study on informational reliability. | E36: Abstract Background Artificial intelligence (AI) and large language models (LLMs) like ChatGPT have transformed information retrieval, including in healthcare. ChatGPT, trained on diverse datasets, can provide medical advice but faces ethical and accuracy concerns. This study evaluates the accuracy of ChatGPT-3.5's answers to frequently asked questions about oral cancer, a condition where early diagnosis is crucial for improving patient outcomes. Methods A total of 20 questions were asked to ChatGPT-3.5, selected from Google Trends and questions asked by patients in the clinic. The responses provided by ChatGPT were evaluated for accuracy by medical oncologists and oral and maxillofacial radiologists. Inter-rater agreement was assessed using Fleiss’s and Cohen kappa tests. The scores given by the specialties were compared with the Mann-Whitney U test. The references provided by ChatGPT-3.5 were evaluated for authenticity. Results Of the 80 responses from 20 questions, 41 (51.25%) were rated as very good, 37 (46.25%) as good, 2 (2.50%) as acceptable. There was no significant difference between oral and maxillofacial radiologists and medical oncologists in all 20 questions. Of the 81 references to ChatGPT-3.5 answers, only 13 were scientific articles, 10 were fake, and the remaining references were data from websites. Conclusion ChatGPT provided reliable information about oral cancer and did not provide incorrect information and suggestions. However, all information provided by… | F36: Çi Ti R, Mesude | G36: 2025 | H36: BMC oral health | I36: 10.1186/s12903-025-05479-4 | J36: 39833819.0 | K36: Journal article (original research) | L36: English | M36: Oral & maxillofacial surgery; Oral medicine / oral pathology | N36: Amass BiomedCore (connector); Consensus (connector); Crossref; DOAJ; Europe PMC; PubMed/MEDLINE; Semantic Scholar | O36: INCLUDE | P36: - | Q36: oral cancer FAQs from Google Trends and patients; GPT-3.5 accuracy | R36: INCLUDE | S36: - | T36: oral cancer FAQs Google Trends/patients; ChatGPT-3.5; accuracy rated | U36: =IF(AND(O36=R36,O36<>"UNSURE"),"Agree","Conflict/Unsure") -> Agree | Y36: 0.909 | Z36: 146 | AA36: No | AD36: INCLUDE | AE36: - | AF36: R1 = R2
A37: LLMDENT-0068 | B37: 36 | C37: calibration | D37: Examiner stratification reveals clinically relevant variability in large language model answers to endodontic patient questions. | E37: INTRODUCTION: Large language models (LLMs) are increasingly used by patients seeking endodontic information, yet their clinical reliability and safety in patient-centred communication remain uncertain. METHODS: This study evaluated the clinical reliability and safety of three contemporary LLMs (ChatGPT GPT-4o, Claude Sonnet 4.5, and Gemini 3 Flash) using 50 patient-centred endodontic questions (35 frequently asked questions and 15 scenario-based prompts). Each question was submitted six times per model in independent sessions. Responses were anonymised and independently assessed by four examiners using a structured Clinical Reliability and Safety Framework. Due to poor inter-examiner agreement, analyses were conducted using examiner stratification. Reproducibility was assessed using word count variability, embedding-based semantic similarity, and lexical distance metrics. RESULTS: Statistically significant differences in clinical reliability were observed across all examiners. ChatGPT consistently received the lowest scores, whereas Gemini most frequently achieved the highest ratings. Model differentiation was clearer for structured frequently asked questions and selected clinical domains than for scenario-based prompts. All models demonstrated stable response lengths across repeated runs. Gemini showed the highest semantic consistency despite greater surface-level rewording. DISCUSSION: Contemporary LLMs demonstrate clinically meaningful variability beyond factual accuracy, … | F37: Alqahtani, Saeed S; Algarni, Hmoud Ali; Alonazi, Meshal Aber; Iqbal, Azhar; Khattak, Osama; Jothish, Ravi; Karobari, Mohmed Isaqali | G37: 2026 | H37: Frontiers in medicine | I37: 10.3389/fmed.2026.1819087 | J37: 42100249.0 | K37: Journal article (original research) | L37: English | M37: Endodontics | N37: Crossref; DOAJ; Europe PMC; PubMed/MEDLINE; Semantic Scholar | O37: INCLUDE | P37: - | Q37: endodontic patient questions; GPT-4o Claude Gemini; reliability and safety | R37: INCLUDE | S37: - | T37: patient endodontic FAQs and scenarios; three LLMs; reliability safety framework | U37: =IF(AND(O37=R37,O37<>"UNSURE"),"Agree","Conflict/Unsure") -> Agree | Y37: 0.775 | Z37: 246 | AA37: No | AD37: INCLUDE | AE37: - | AF37: R1 = R2
A38: LLMDENT-0314 | B38: 37 | C38: calibration | D38: Functional and Existential AI Dependence in Dental Students and Professionals: A Hybrid Network Analysis. | E38: INTRODUCTION: Generative artificial intelligence (AI) tools are now embedded in dental teaching and clinical learning, yet little is known about how reliance on them is psychologically organised in dental students and professionals. This study mapped how two forms of AI dependence relate to problematic social media use, anxiety, and attentional control. MATERIALS AND METHODS: Cross-sectional online survey of 342 Brazilian dental students and professionals. Latent factor scores from confirmatory factor analysis were combined with observed variables in a hybrid network. Network structure, centrality, and stability were estimated with regularised Gaussian graphical modelling and bootstrapping. RESULTS: Functional Dependence (FD) and Existential Dependence (ED) were positively associated with each other (partial r = 0.447). FD was negatively and ED positively associated with anxiety (r = -0.146 and 0.264); both were positively associated with problematic social media use, ED more strongly (r = 0.237 vs. 0.168). Attentional focusing was negatively associated with anxiety and problematic social media use, but not with either form of AI dependence. Centrality estimates were not stable (CS-coefficient = 0.05, below the recommended 0.25) and are not used to rank nodes. DISCUSSION: Instrumental and emotional reliance on AI did not behave as one construct. Only ED was positively associated with anxiety. CONCLUSIONS: Dental education programmes introducing AI should address not only tech… | F38: Gasparello, Gil Guilherme; Tirkkonen, Otso; Machado, Rosilene Andrea; Bastos, Susiane Queiroz; Tanaka, Orlando Motohiro | G38: 2026 | H38: European journal of dental education : official journal of the Association for Dental Education in Europe | I38: 10.1111/eje.70311 | J38: 42762081.0 | K38: Journal article (original research) | L38: English | M38: Dental education / exams; General dentistry / cross-specialty | N38: Europe PMC; PubMed/MEDLINE; Semantic Scholar | O38: EXCLUDE | P38: E3 | Q38: survey AI dependence in dental students and professionals | R38: EXCLUDE | S38: E3 | T38: survey of AI dependence in dental students/professionals | U38: =IF(AND(O38=R38,O38<>"UNSURE"),"Agree","Conflict/Unsure") -> Agree | Y38: 0.136 | Z38: 1573 | AA38: No | AD38: EXCLUDE | AE38: E3 | AF38: R1 = R2
A39: LLMDENT-0042 | B39: 38 | C39: calibration | D39: Evaluating Dental Students' Perspectives on Artificial Intelligence (AI)-Driven Large Language Models in Education in Saudi Arabia. | E39: OBJECTIVES: This study explores the perspectives of dental students in Saudi Arabia regarding the integration of large language models (LLMs) in dental education. It aims to understand their familiarity, utilisation and perceptions of these tools, while addressing the potential benefits, risks, and ethical considerations associated with their use. METHODS: A cross-sectional survey was conducted between January and March 2024, involving 1370 dental students from various institutions across Saudi Arabia. The survey included multiple-choice questions and Likert scale items, assessing familiarity, usage patterns, and perceptions of LLMs. Statistical analyses were performed to identify significant associations between demographic variables and students' familiarity, utilisation, and perceptions of LLMs. RESULTS: The survey revealed broad familiarity with LLMs, with 58.1% of participants being aware of their capabilities. Usage patterns varied, with high engagement in tools like ChatGPT and Google Translate. Significant gender, educational level and regional differences were observed, with males and postgraduate residents showing higher familiarity and utilisation rates. However, ethical concerns, including the potential for plagiarism and academic dishonesty, were prevalent, with only 15% of students reporting that their institutions had specific guidelines for LLM use. CONCLUSION: The study highlights the need for a controlled and ethically informed approach to integrating LLMs i… | F39: Al-Khalifa, Khalifa S; Ahmed, Walaa Magdy; Azhari, Amr Ahmed; Ibrahim, Amir I O; Al-Saljah, Reham S; Ali, Ramy Moustafa Moustafa; Ainoosah, Sultan; Alfaraj, Amal | G39: 2026 | H39: European journal of dental education : official journal of the Association for Dental Education in Europe | I39: 10.1111/eje.70042 | J39: 41014093.0 | K39: Journal article (original research) | L39: English | M39: Preventive dentistry / dental public health; Dental education / exams | N39: Europe PMC; PubMed/MEDLINE; Semantic Scholar | O39: EXCLUDE | P39: E3 | Q39: dental student perceptions survey LLMs in education | R39: EXCLUDE | S39: E3 | T39: dental student perspectives survey on LLMs in education | U39: =IF(AND(O39=R39,O39<>"UNSURE"),"Agree","Conflict/Unsure") -> Agree | Y39: 0.127 | Z39: 1621 | AA39: No | AD39: EXCLUDE | AE39: E3 | AF39: R1 = R2
A40: LLMDENT-0201 | B40: 39 | C40: calibration | D40: Structured Visual Evidence Decomposition for Evidence-Grounded Multimodal Screening of Obstructive Sleep Apnea-Hypopnea Syndrome | E40: Effective pre-polysomnography screening for obstructive sleep apnea-hypopnea syndrome (OSAHS) requires combining clinical risk factors with visible craniofacial and neck cues. Directly prompting general-purpose multimodal foundation models for medical yes/no decisions can yield unstable, poorly calibrated outputs. We propose EviOSAHS, an evidence-grounded multimodal reasoning framework that separates image-only anatomical evidence acquisition from final clinical adjudication. Each frontal facial image is decomposed into seven fixed anatomical queries covering the neck, chin, mouth, face/neck fat, lower jaw, midface, and nose. Visual responses are converted into structured evidence cards recording target anatomy, visibility, risk direction, evidence strength, confidence, and a concise summary. These cards are combined with a cleaned clinical profile only in the final stage, where a large language model performs balanced binary screening adjudication. We evaluated EviOSAHS on a 642-subject cohort, mapping normal subjects to screening-negative and mild, moderate, or severe OSAHS subjects to screening-positive. EviOSAHS achieved 88.47% accuracy, 94.86% sensitivity, 93.74% F1-score, and a 5.14% false-negative rate, outperforming clinical-only prompting, direct multimodal prompting, and naive two-stage pipelines under a unified protocol. Ablations showed that seven-question visual decomposition and balanced final adjudication were critical to the high-sensitivity operating point. A… | F40: Chen Zhan; Yingchen Wei; Xiao-Yu Tan; Jingjing Huang; Xihe Qiu | G40: 2026 | H40: ArXiv | I40: 10.48550/arxiv.2606.00087 | K40: Preprint | L40: English (automatically detected) | M40: General dentistry / cross-specialty | N40: Semantic Scholar | O40: EXCLUDE | P40: E1 | Q40: OSAHS screening from facial images; custom multimodal framework | R40: EXCLUDE | S40: E1 | T40: OSAHS screening from facial images; not dental care; diagnostic | U40: =IF(AND(O40=R40,O40<>"UNSURE"),"Agree","Conflict/Unsure") -> Agree | Y40: 0.14 | Z40: 1555 | AA40: No | AD40: EXCLUDE | AE40: E1 | AF40: R1 = R2
A41: LLMDENT-0191 | B41: 40 | C41: calibration | D41: Navigating Oral Cancer Management: Combining Artificial Intelligence and Clinical Guidelines for Optimal Decision-Making. | E41: Abstract Introduction Decision-making is one of the most difficult and important tasks performed by surgeons. Clinical guidelines and, more recently, Artificial Intelligence (AI) have been implemented to support these decisions. However, there is a paucity of research exploring the impact of AI on surgical decision-making strategies. Objective To evaluate the accuracy of AI in informing clinical decision-making for the treatment of advanced oral cancer. Methods Structured questions based on seven selected clinical recommendations were formulated and processed through multiple large language model (LLM) platforms. Claude (Sonnet 3.5) was used to identify discrepancies between established guidelines and LLM-generated responses. Subsequently, three subject matter experts assessed the identified differences to evaluate their clinical significance. Results Analysis of the 28 generated responses revealed that 21 (75%) showed congruence between LLM outputs and established guideline recommendations. In three instances, guidelines provided significantly more comprehensive content than LLM responses. One LLM response contained additional relevant information, while three responses were contradictory to the guidelines. Conclusion The LLMs demonstrated 75% concordance with guideline recommendations and should be considered complementary tools for established clinical guidelines. | F41: Castro, Mario Augusto Ferrari de; Dedivitis, Rogério Aparecido; Matos, Leandro Luongo de; Gimenes, Paulo Vitor Sóla; Duarte, Bruno Pelinson Fogaça; Kowalski, Luiz Paulo | G41: 2026 | H41: International archives of otorhinolaryngology | I41: 10.1055/a-2852-9642 | J41: 42603075.0 | K41: Journal article (original research) | L41: English | M41: Oral medicine / oral pathology | N41: Europe PMC; PubMed/MEDLINE; Semantic Scholar | O41: EXCLUDE | P41: E3 | Q41: oral cancer guideline-based surgical decision-making | R41: EXCLUDE | S41: E3 | T41: advanced oral cancer treatment decisions vs guidelines for surgeons | U41: =IF(AND(O41=R41,O41<>"UNSURE"),"Agree","Conflict/Unsure") -> Agree | Y41: 0.495 | Z41: 477 | AA41: No | AD41: EXCLUDE | AE41: E3 | AF41: R1 = R2
A42: LLMDENT-1020 | B42: 41 | C42: calibration | D42: Diagnostic accuracy of large language models in ICOP-based orofacial pain diagnosis: A comparative study. | E42: OBJECTIVE: To compare the diagnostic performance of ChatGPT 5.5, Claude Opus 4.1, Gemini 3 Flash, and Grok 4 in International Classification of Orofacial Pain (ICOP)-based clinical scenarios. METHODS: Thirty ICOP diagnoses were randomly selected, and corresponding clinical scenarios were manually developed. Each scenario was submitted to all models using standardized prompts in independent sessions. Two blinded evaluators assessed primary diagnosis accuracy, subclassification accuracy, clinical interpretation, and management recommendations. RESULTS: Overall performance differed significantly among models (p < .001). Grok 4 achieved the highest total score and outperformed the other models. No significant differences were found among ChatGPT 5.5, Gemini 3 Flash, and Claude Opus 4.1. Subclassification accuracy was consistently lower than primary diagnosis accuracy, while management recommendations did not differ significantly. CONCLUSION: LLM performance varied across ICOP-based scenarios. Although Grok 4 showed the highest diagnostic concordance, current LLMs should support, not replace, clinician judgment. | F42: Şimşek, Mehmet Sait; Esen, Enis; Koparal, Mahmut | G42: 2026 | H42: Cranio : the journal of craniomandibular practice | I42: 10.1080/08869634.2026.2702999 | J42: 42439775.0 | K42: Journal article (original research) | L42: English | M42: TMD / orofacial pain | N42: Europe PMC; PubMed/MEDLINE; Semantic Scholar | O42: EXCLUDE | P42: E3 | Q42: ICOP clinical scenarios diagnostic accuracy | R42: EXCLUDE | S42: E3 | T42: ICOP orofacial pain clinical scenarios; diagnostic accuracy for clinicians | U42: =IF(AND(O42=R42,O42<>"UNSURE"),"Agree","Conflict/Unsure") -> Agree | Y42: 0.357 | Z42: 728 | AA42: No | AD42: EXCLUDE | AE42: E3 | AF42: R1 = R2
A43: LLMDENT-0379 | B43: 42 | C43: calibration | D43: The role of artificial intelligence in providing accurate and reliable information on surgically-assisted rapid palatal expansion: A cross-sectional study. | E43: INTRODUCTION: This study aimed to evaluate the accuracy, reliability, and comprehensibility of information about surgically-assisted rapid palatal expansion provided by language models based on artificial intelligence (AI). METHODS: A cross-sectional content analysis was conducted on the responses to surgically-assisted rapid palatal expansion-related questions by ChatGPT-4 (OpenAI LLC, San Francisco, Calif), Gemini (Alphabet Inc, Mountain View, Calif), and Copilot (Microsoft, Redmond, Wash). In total, 115 questions (categorized into 11 domains) were created by 3 orthodontists and 1 oral and maxillofacial surgeon. The accuracy of the answers generated by the AI language models was independently evaluated by the same experts via a 5-point Likert scale. To test the relationships among categorical variables, when the sample size assumption was met, the Pearson chi-square test was used. However, when the sample size assumption was not met, Fisher's exact test was applied. Analyses were performed in SPSS (version 27; IBM, Armonk, NY). RESULTS: The responses of the AI types presented a general homogeneous distribution, with no statistically significant difference between the types of AI and the types of responses (P >0.05). Although there were no significant differences, ChatGPT-4 had the highest objectively true rate. In contrast, Gemini produced answers with more balanced accuracy, whereas Copilot had the highest number of false answers. CONCLUSIONS: These findings reveal that th… | F43: Hatipoğlu, Şirin; Çifçi Özkan, Esra; Konca Taşova, Fatma Aslı; Özdal Zincir, Özge | G43: 2026 | H43: American journal of orthodontics and dentofacial orthopedics : official publication of the American Association of Orthodontists, its constituent societies, and the American Board of Orthodontics | I43: 10.1016/j.ajodo.2025.08.015 | J43: 41055620.0 | K43: Journal article (original research) | L43: English | M43: Orthodontics; Oral & maxillofacial surgery | N43: Europe PMC; PubMed/MEDLINE; Semantic Scholar | O43: INCLUDE | P43: - | Q43: SARPE questions; GPT-4 Gemini Copilot; accuracy Likert; audience unclear | R43: INCLUDE | S43: - | T43: SARPE information; ChatGPT-4 Gemini Copilot; expert accuracy Likert; audience unclear | U43: =IF(AND(O43=R43,O43<>"UNSURE"),"Agree","Conflict/Unsure") -> Agree | Y43: 0.809 | Z43: 219 | AA43: No | AD43: INCLUDE | AE43: - | AF43: R1 = R2
A44: LLMDENT-1305 | B44: 43 | C44: calibration | D44: Ai Chatbots for Pediatric Fluoride Education: An Effectiveness Study | E44: Abstract Background: Fluoride is a cornerstone of preventive pediatric dentistry, yet public concerns and online misinformation continue to undermine its acceptance. With the rise of large language model-based (LLM) chatbots, artificial intelligence (AI) tools have emerged as potential resources for delivering accessible, evidence-based health information. Objective: This study aims to evaluate the performance of three advanced AI chatbots—ChatGPT-4.o, Google Gemini Pro, and DeepSeek V3—in providing fluoride-related information to parents and caregivers, with a specific focus on pediatric dental health. Methods: Twenty frequently asked fluoride-related questions were presented to each chatbot in standardized sessions. Responses were assessed by three blinded evaluators using validated tools: EQIP, DISCERN, Global Quality Scale (GQS), Flesch Reading Ease Score (FRES), Flesch-Kincaid Reading Grade Level (FKRGL), and iThenticate similarity index. Inter-rater reliability was ensured via intraclass correlation coefficients (ICCs). Statistical analysis was performed using ANOVA or Kruskal–Wallis tests, with appropriate post-hoc methods. Results: ChatGPT-4.o outperformed the other models in EQIP and DISCERN scores (p Conclusion: Among the evaluated AI chatbots, ChatGPT-4.o demonstrated superior performance in conveying fluoride-related information in a clear, reliable, and evidence-based manner. While promising as educational tools in pediatric oral health, these models should be co… | F44: Karamüftüoğlu N; Varol EA; Bal C | G44: 2025 | H44: Research Square | I44: 10.21203/rs.3.rs-6993451/v1 | K44: Preprint | L44: English (automatically detected) | M44: Pediatric dentistry; Restorative dentistry / cariology; Preventive dentistry / dental public health; Dental education / exams | N44: Europe PMC (Preprint) | O44: INCLUDE | P44: - | Q44: preprint; parent fluoride FAQs; 3 chatbots; DISCERN GQS EQIP | R44: INCLUDE | S44: - | T44: preprint; parent fluoride FAQs; three chatbots; EQIP DISCERN GQS | U44: =IF(AND(O44=R44,O44<>"UNSURE"),"Agree","Conflict/Unsure") -> Agree | Y44: 0.965 | Z44: 103 | AA44: No | AD44: INCLUDE | AE44: - | AF44: R1 = R2
A45: LLMDENT-1104 | B45: 44 | C45: calibration | D45: Comparing Manual and ChatGPT Deep Research on Systematic Search and Selection in the PubMed Database on the Topic of Dental Implantology. | E45: INTRODUCTION: Dental implantology has seen rapid technological advancements, with artificial intelligence (AI) increasingly integrated into diagnostic, planning, and surgical processes. The release of chat-generative pretrained transformer (ChatGPT) and its subsequent updates, including the deep research function, presents opportunities for AI-assisted systematic reviews. However, its efficacy compared to traditional manual research has not been researched. MATERIALS AND METHODS: A systematic review was conducted on May 6, 2025, to evaluate recent innovations in dental implantology and AI. Two parallel searches were performed: one using ChatGPT 4.1's deep research tool in the PubMed database and another manual PubMed search by two independent reviewers. Both searches used identical keywords and Boolean operators targeting studies from 2020 to 2025. Inclusion criteria were peer-reviewed studies related to implant design, osseointegration, guided placement, and other predefined outcomes. RESULTS: The manual search identified 124 articles, of which 23 met the inclusion criteria. ChatGPT retrieved 114 articles, selected 13 for inclusion, yet only included 11 in its synthesis. Two cited articles by the AI software were nonexistent, and numerous relevant studies were not retrieved, whereas the remaining articles were correct and found by manual search as well. ChatGPT had high specificity (98%) and low sensitivity (47.8%), with a statistically significant difference compared to man… | F45: Bencze, Bulcsú; Sokolowski, Alwin; Lee, Jae-Hyun; Hermann, Péter; Hegedüs, Tamás; Kozuma, Wataru; Ikumi, Reo; Payer, Michael; Salgado-Peralvo, Ángel-Orión; Végh, Dániel | G45: 2025 | H45: International journal of dentistry | I45: 10.1155/ijod/2677641 | J45: 41122309.0 | K45: Journal article (original research) | L45: English | M45: Implant dentistry | N45: Crossref; DOAJ; Europe PMC; PubMed/MEDLINE; Semantic Scholar | O45: EXCLUDE | P45: E2 | Q45: ChatGPT deep research as literature search tool | R45: EXCLUDE | S45: E2 | T45: ChatGPT deep research as literature search tool | U45: =IF(AND(O45=R45,O45<>"UNSURE"),"Agree","Conflict/Unsure") -> Agree | Y45: 0.157 | Z45: 1458 | AA45: No | AD45: EXCLUDE | AE45: E2 | AF45: R1 = R2
A46: LLMDENT-1795 | B46: 45 | C46: calibration | D46: ChatGPT-4.0 in oral and maxillofacial radiology: prediction of anatomical and pathological conditions from radiographic images. | E46: Introduction: ChatGPT has the ability to generate human-like text, analyze and understand medical images using natural Language processing (NLP) algorithms. It can generate real-time diagnosis and recognize patterns and learn from previous cases to improve accuracy by combining patient history, symptoms, and image characteristics. It has been used recently for learning about maxillofacial diseases, writing and translating radiology reports, and identifying anatomical landmarks, among other things. Materials and methods: In this study, 52 radiographic images were queried on the OpenAI application ChatGPT-4.0. The responses were evaluated with and without using clues for specific radiographs to see if adding clues during prompting improved diagnostic accuracy. Results: The true prediagnosis rate without any clue was 30.7%. By adding one clue this rate significantly increased to 56.9%. There was not a significant difference in accurate diagnosis of anatomical landmarks, cysts, and tumors (p&gt;0.05). However, including internal structure information improved the diagnostic accuracy (p&lt;0.05) Conclusion: GPT-4.0 showed a tendency to misdiagnose closely located anatomical structures and by adding additional clues its performance showed improvement, while its ability to recognize diverse differential diagnoses remains limited. | F46: Kahalian, Shila; Rajabzadeh, Marieh; Öçbe, Melisa; Medisoglu, Mahmut Sabri | G46: 2024 | H46: Folia medica | I46: 10.3897/folmed.66.e135584 | J46: 39774357.0 | K46: Journal article (original research) | L46: English | M46: Oral & maxillofacial surgery; Oral & maxillofacial radiology | N46: DOAJ; Europe PMC; PubMed/MEDLINE; Semantic Scholar | O46: EXCLUDE | P46: E3 | Q46: GPT-4 radiographic image diagnosis | R46: EXCLUDE | S46: E3 | T46: ChatGPT-4 radiographic image diagnosis | U46: =IF(AND(O46=R46,O46<>"UNSURE"),"Agree","Conflict/Unsure") -> Agree | Y46: 0.197 | Z46: 1264 | AA46: No | AD46: EXCLUDE | AE46: E3 | AF46: R1 = R2
A47: LLMDENT-1843 | B47: 46 | C47: calibration | D47: Optimization of Oral Rehabilitation: Use of Artificial Intelligence in the Manufacture of Protocol-Type Provisional Prostheses with Immediate Loading for Maxillae | E47: The use of Large Language Model (LLM) technologies, such as Artificial Intelligence (AI) with Deep Learning and Machine Learning software, has become commonplace in surgical planning, enabling the capture, manipulation and digital planning of immediately loaded provisional prostheses for dental implants. Materials and Methods: this literature review a search was made for scientific articles in virtual databases: PUBMED, ScIELO, Google Scholar, LILACS, BVS, ResearchGate. Articles that were not part of dentistry were excluded based on the theme of the Abstract. The 28 articles pertinent to dentistry and the theme of the abstract were included and fully analyzed. The following were aligned and distributed in the literature review: systematic reviews, literature reviews, clinical cases, laboratory studies, books, theses and dissertations. Conclusion: The improvement of Artificial Intelligence in dentistry is enabling better planning and practical-surgical-prosthetic execution with the creation and printing of provisional prostheses with immediate loading, better retention, occlusal stability, less repair and a pleasant biopsychosocial sensation, since it eliminates instability due to the mechanical displacement of overdentures. | F47: J. Nascimento; J. Lima; Danielly Cristina Marques de Castro | G47: 2024 | H47: Journal of Advances in Medicine and Medical Research | I47: 10.9734/jammr/2024/v36i45408 | K47: Review (narrative) | L47: English (automatically detected) | M47: Implant dentistry | N47: Semantic Scholar | O47: EXCLUDE | P47: E2 | Q47: narrative review AI in prosthesis manufacture; not chatbot | R47: EXCLUDE | S47: E2 | T47: narrative review AI in provisional prosthesis manufacturing | U47: =IF(AND(O47=R47,O47<>"UNSURE"),"Agree","Conflict/Unsure") -> Agree | Y47: 0.039 | Z47: 2001 | AA47: No | AD47: EXCLUDE | AE47: E2 | AF47: R1 = R2
A48: LLMDENT-0458 | B48: 47 | C48: calibration | D48: Applications of ChatGPT in Dentistry: A Review (Preprint) | E48: BACKGROUND ChatGPT offers promising applications across multiple dental domains, particularly in education and patient communication. However, current evidence remains limited by significant methodological heterogeneity among evaluation approaches. OBJECTIVE The objective of this review was to evaluate the application of ChatGPT across various dental disciplines and to examine the methodologies used to assess its performance. METHODS We searched the MEDLINE (via PubMed), Cochrane Library, Google Scholar, Scopus, and Web of Science databases for English-language studies evaluating ChatGPT in dental contexts. Extracted outcomes included the accuracy, reliability, readability, consistency, and usefulness of the ChatGPT-generated responses. RESULTS We included 26 studies categorized into five themes: clinical question answering, clinical decision support and diagnosis, patient communication and education, dental research, and dental education. Performance varied widely, with accuracy ranging from 25% to over 90% based on task complexity. ChatGPT demonstrated strong capabilities in generating structured responses and patient-geared educational materials. However, substantial methodological variability in prompt design, evaluator characteristics, and outcome definitions limited direct cross-study comparisons. Frequently reported limitations included inconsistent accuracy, reduced readability for lay audiences, a lack of reproducibility testing, hallucinated misinformation, and an a… | F48: Kabbarah, Alaa; Alwafi, Abdulraheem A.; Rajeh, Mona T.; Sabbahi, Dania A.; Almutairi, Sarah; Meisha, Dalia E. | G48: 2026 | I48: 10.2196/preprints.105330 | K48: Preprint | L48: English (automatically detected) | M48: Dental education / exams; General dentistry / cross-specialty | N48: Crossref | O48: EXCLUDE | P48: E5 | Q48: review of ChatGPT applications in dentistry | R48: EXCLUDE | S48: E5 | T48: review of ChatGPT applications in dentistry | U48: =IF(AND(O48=R48,O48<>"UNSURE"),"Agree","Conflict/Unsure") -> Agree | Y48: 0.291 | Z48: 900 | AA48: No | AD48: EXCLUDE | AE48: E5 | AF48: R1 = R2
A49: LLMDENT-0213 | B49: 48 | C49: calibration | D49: AI in Oral Health Surveillance: Critical Review. | E49: Artificial intelligence (AI) holds transformative potential for advancing oral health surveillance by streamlining data collection, integration, and dissemination. This review critically synthesizes AI applications in oral health surveillance, highlighting its roles in 1) mapping population-level trends and oral health inequities using machine learning on epidemiological data; 2) enabling remote screening of oral diseases/conditions, including caries, oral hygiene, gingivitis, oral cancer, and malocclusion from intraoral images via computer vision models; and 3) integrating multimodal data through emerging large language models (LLMs) to enhance precision public health. We clarify the comparative strengths of distinct AI modeling for processing the primary data types in surveillance: structured clinical records, unstructured images, and integrated multimodal data. Traditional machine learning methods have been effectively applied to map population-level oral health disparities and identify risk factors but are constrained to structured data. Computer vision methods excel in individual-level diagnostics using intraoral photographs. To translate such capability into scalable surveillance, it is recommended to establish standardized imaging protocols for nonclinical settings, develop scalable models for fine-grained feature extraction, and implement reliable evaluation. These steps are essential to address pervasive challenges, including inconsistent image quality, domain shift,… | F49: Chen, Z; Liu, P; Han, K; Liao, P; Yang, Y; Wong, M C M; Yiu, C K Y; Lo, E C M | G49: 2026 | H49: Journal of dental research | I49: 10.1177/00220345261434568 | J49: 41958249.0 | K49: Review (narrative) | L49: English | M49: Orthodontics; Periodontology; Oral & maxillofacial surgery; Restorative dentistry / cariology; Oral medicine / oral pathology; Oral & maxillofacial radiology; Preventive dentistry / dental public health | N49: Europe PMC; PubMed/MEDLINE; Semantic Scholar | O49: EXCLUDE | P49: E2 | Q49: review AI oral health surveillance; mainly ML/computer vision | R49: EXCLUDE | S49: E2 | T49: critical review AI oral health surveillance; mainly ML/computer vision | U49: =IF(AND(O49=R49,O49<>"UNSURE"),"Agree","Conflict/Unsure") -> Agree | Y49: 0.019 | Z49: 2057 | AA49: No | AD49: EXCLUDE | AE49: E2 | AF49: R1 = R2
A50: LLMDENT-1986 | B50: 49 | C50: calibration | D50: A systematic review and meta-analysis on ChatGPT and its utilization in medical and dental research. | E50: UNLABELLED: Since its release, ChatGPT has taken the world by storm with its utilization in various fields of life. This review's main goal was to offer a thorough and fact-based evaluation of ChatGPT's potential as a tool for medical and dental research, which could direct subsequent research and influence clinical practices. METHODS: Different online databases were scoured for relevant articles that were in accordance with the study objectives. A team of reviewers was assembled to devise a proper methodological framework for inclusion of articles and meta-analysis. RESULTS: 11 descriptive studies were considered for this review that evaluated the accuracy of ChatGPT in answering medical queries related to different domains such as systematic reviews, cancer, liver diseases, diagnostic imaging, education, and COVID-19 vaccination. The studies reported different accuracy ranges, from 18.3 % to 100 %, across various datasets and specialties. The meta-analysis showed an odds ratio (OR) of 2.25 and a relative risk (RR) of 1.47 with a 95 % confidence interval (CI), indicating that the accuracy of ChatGPT in providing correct responses was significantly higher compared to the total responses for queries. However, significant heterogeneity was present among the studies, suggesting considerable variability in the effect sizes across the included studies. CONCLUSION: The observations indicate that ChatGPT has the ability to provide appropriate solutions to questions in the medical an… | F50: Bagde, Hiroj; Dhopte, Ashwini; Alam, Mohammad Khursheed; Basri, Rehana | G50: 2023 | H50: Heliyon | I50: 10.1016/j.heliyon.2023.e23050 | J50: 38144348.0 | K50: Systematic review / meta-analysis | L50: English | M50: Oral & maxillofacial radiology | N50: Crossref; DOAJ; Europe PMC; Europe PMC (Preprint); PubMed/MEDLINE; Semantic Scholar | O50: EXCLUDE | P50: E5 | Q50: systematic review/meta-analysis ChatGPT medical and dental research | R50: EXCLUDE | S50: E5 | T50: systematic review and meta-analysis | U50: =IF(AND(O50=R50,O50<>"UNSURE"),"Agree","Conflict/Unsure") -> Agree | Y50: 0.203 | Z50: 1238 | AA50: No | AD50: EXCLUDE | AE50: E5 | AF50: R1 = R2
A51: LLMDENT-0989 | B51: 50 | C51: calibration | D51: Mapping the Scientific Landscape of Artificial Intelligence in Endodontics: A Bibliometric Analysis. | E51: INTRODUCTION: The aim of this bibliometric study was to systematically map the evolution, structural characteristics and methodological profile of artificial intelligence (AI) research in endodontics by analysing publication trends, collaboration networks, thematic development and citation impact. MATERIALS AND METHODS: A bibliometric analysis was conducted using publications indexed in the Web of Science Core Collection, Scopus and PubMed from 1 January 1990 to 19 August 2025. Following deduplication and eligibility screening, 245 articles were included. Authorship, country-level collaboration and keyword co-occurrence networks were analysed using VOSviewer. Citation data were harmonised across databases using regression-based normalisation. Negative binomial regression was applied to evaluate the association between citation counts and publication year, document type and open-access status. RESULTS: AI-related research in endodontics showed minimal activity before 2020, followed by rapid growth driven predominantly by deep learning (DL) based imaging applications. Periapical radiographs (PA) and cone-beam computed tomography (CBCT) were the most frequently used data sources. China accounted for the highest publication volume, whereas the United States demonstrated the greatest citation-weighted influence and centrality within international collaboration networks. Keyword co-occurrence analysis identified six thematic clusters, dominated by radiographic diagnostics, with a r… | F51: Çatmabacak, Ekin Deniz; Eren, Ahmet Kerem; Çetinkaya Valandova, İrem | G51: 2026 | H51: International endodontic journal | I51: 10.1111/iej.70107 | J51: 41614669.0 | K51: Review (narrative) | L51: English | M51: Endodontics; Oral & maxillofacial radiology | N51: Europe PMC; PubMed/MEDLINE; Semantic Scholar; Wiley Scholar Gateway (connector, full text) | O51: EXCLUDE | P51: E2 | Q51: bibliometric analysis AI in endodontics; mostly deep learning imaging | R51: EXCLUDE | S51: E5 | T51: bibliometric analysis AI in endodontics | U51: =IF(AND(O51=R51,O51<>"UNSURE"),"Agree","Conflict/Unsure") -> Agree | Y51: 0.044 | Z51: 1986 | AA51: No | AD51: EXCLUDE | AE51: E5 | AF51: R1 = R2
A52: LLMDENT-0933 | B52: 51 | C52: calibration | D52: Accuracy and Completeness of Contemporary Large Language Models in Prosthodontics: An Expert-Based Comparative Study | E52: Purpose: To compare the scientific accuracy and response completeness of four contemporary LLMs: ChatGPT-5.2, Gemini 3, Copilot, and DeepSeek-V3.2 across major prosthodontic domains and question formats.Methods: Fifty prosthodontic questions covering removable prosthodontics, fixed prosthodontics, implantology, temporomandibular disorders and occlusion, dental materials science were developed from standard textbooks and clinical guidelines. Questions were presented in yes/no, multiple-choice, and open-ended formats to reflect different levels of clinical reasoning. Responses generated by ChatGPT-5.2 (OpenAI), Gemini 3 (Google), Microsoft Copilot (Microsoft), and DeepSeek-V3.2 were independently evaluated by five prosthodontists using Likert-based scales for accuracy and completeness. Inter-rater reliability was assessed to ensure scoring consistency, and model performances were compared across domains and question types using nonparametric statistical tests.Results: Overall accuracy differed significantly among the four models (p0.05), although descriptive trends suggested slightly higher scores for yes/no questions and lower scores for multiple-choice items. Response completeness also varied significantly across models (p0.05).Conclusion: Contemporary large language models demonstrate acceptable theoretical performance in prosthodontics; however, clinically relevant differences persist in response completeness and consistency. These models may support prosthodontic education… | F52: Elif Yiğit İren; Hatice Betül Üçkuyu | G52: 2026 | H52: Acıbadem Üniversitesi Sağlık Bilimleri Dergisi | I52: 10.31067/acusaglik.1956329 | K52: Journal article (original research) | L52: English (automatically detected) | M52: Implant dentistry; Prosthodontics; TMD / orofacial pain; Dental education / exams | N52: Semantic Scholar | O52: EXCLUDE | P52: E3 | Q52: textbook/guideline prosthodontic questions incl MCQ; professional knowledge | R52: EXCLUDE | S52: E3 | T52: textbook-based prosthodontic yes/no MCQ open questions; professional knowledge | U52: =IF(AND(O52=R52,O52<>"UNSURE"),"Agree","Conflict/Unsure") -> Agree | Y52: 0.645 | Z52: 340 | AA52: Yes | AB52: EXCLUDE | AC52: Textbook and guideline prosthodontic questions incl MCQ; education framing | AD52: EXCLUDE | AE52: E3 | AF52: R1 = R2
A53: LLMDENT-1090 | B53: 52 | C53: calibration | D53: Evaluation of AI-based chatbot responses to orthodontic retention-related patient questions: a comparative analysis | E53: Aims: This study aimed to evaluate and compare the quality, accuracy, and readability of orthodontic retention-related information provided by five AI-based chatbot platforms: ChatGPT-4, Copilot, Gemini, MediSearch, and OpenEvidence. Methods: A set of 25 commonly asked patient-oriented questions on orthodontic retention was submitted to each chatbot. Responses were evaluated using five key metrics: EQIP (Ensuring Quality Information for Patients), Reliability Score, Global Quality Score (GQS), SMOG Readability Index, and Similarity Index. Mean±standard deviation values were calculated. Kruskal-Wallis and Dunn’s post-hoc tests were used to assess statistical differences. Results: MediSearch and OpenEvidence outperformed others in EQIP and Reliability scores. ChatGPT-4 generated the most original content with the lowest Similarity Index. SMOG readability was significantly better for ChatGPT-4, while MediSearch and OpenEvidence produced more technically complex language. Statistically significant differences (p<0.05) were found between platforms in EQIP, SMOG, and Similarity Index metrics. Conclusion: Performance among AI chatbots varies significantly in delivering orthodontic retention guidance. While medical-specific tools offer superior accuracy and reliability, general-purpose models like ChatGPT-4 excel in readability and originality. The results highlight the importance of matching AI platform selection with patient communication goals. | F53: Aşkın, Melis Büşra; Manav, Ömer Can | G53: 2025 | H53: Journal of Dental Sciences and Education | I53: 10.51271/jdse-0059 | K53: Journal article (original research) | L53: English (automatically detected) | M53: Orthodontics | N53: Crossref; Semantic Scholar | O53: INCLUDE | P53: - | Q53: patient questions orthodontic retention; ChatGPT Copilot Gemini plus medical tools; EQIP GQS | R53: INCLUDE | S53: - | T53: patient retention questions; ChatGPT-4 Copilot Gemini plus medical tools; EQIP GQS | U53: =IF(AND(O53=R53,O53<>"UNSURE"),"Agree","Conflict/Unsure") -> Agree | Y53: 1.059 | Z53: 50 | AA53: No | AD53: INCLUDE | AE53: - | AF53: R1 = R2
A54: LLMDENT-0039 | B54: 53 | C54: calibration | D54: Reliability of Multimodal AI for Assessing Preclinical Stainless Steel Crown Preparations: A Comparative Study With Human Experts. | E54: BACKGROUND: Artificial intelligence presents the potential to enhance consistency and objectivity in preclinical pediatric dentistry assessments. AIM: To evaluate the reliability of multimodal artificial intelligence (AI) models (GPT-4o, Claude-3.7-Sonnet-Reasoning, o4-mini, DeepSeek-R1, DeepSeek-V3, and o3) compared to human experts in assessing stainless steel crown (SSC) preparations. DESIGN: This cross-sectional study analyzed 133 SSC preparations (27 mandibular first primary molars, 106 mandibular second primary molars) from dental students. Using a rubric assessing occlusal reduction, proximal reduction, and finishing criteria, five photographs were captured for each preparation. Images were analyzed using a Reflection-of-Thought prompt and compared to human assessments using a conventional p < 0.05 criterion. RESULTS: Claude-3.7-Sonnet-Reasoning demonstrated exceptional agreement with human experts (ICC = 0.89) across all preparations with consistent performance by tooth type. o4-mini showed moderate agreement (ICC = 0.57), GPT-4o weak agreement (ICC = 0.06), and o3 no agreement (ICC = -0.03), while DeepSeek models achieved 0% task completion. Error analysis revealed proximal reduction errors as the most common (39.2%), followed by finishing (33.6%) and occlusal reduction (27.1%) with significant variations in error detections between assessors, particularly for second primary molars. CONCLUSIONS: Claude-3.7-Sonnet Reasoning demonstrates human-expert-level reliability … | F54: Al-Haj Ali, Sanaa N | G54: 2026 | H54: International journal of paediatric dentistry | I54: 10.1111/ipd.70049 | J54: 41199440.0 | K54: Journal article (original research) | L54: English | M54: Prosthodontics; Pediatric dentistry; Dental education / exams | N54: Europe PMC; PubMed/MEDLINE; Semantic Scholar | O54: EXCLUDE | P54: E3 | Q54: multimodal LLM grading student crown preparations; education | R54: EXCLUDE | S54: E3 | T54: multimodal grading of student crown preparation photos | U54: =IF(AND(O54=R54,O54<>"UNSURE"),"Agree","Conflict/Unsure") -> Agree | Y54: 0.298 | Z54: 878 | AA54: No | AD54: EXCLUDE | AE54: E3 | AF54: R1 = R2
A55: LLMDENT-0990 | B55: 54 | C55: calibration | D55: Comparative Evaluation of Large Language Models for Reporting Jaw Lesions on Panoramic Radiographs. | E55: Background/Objectives: The aim of this study was to assess the diagnostic capabilities of three large language model-based artificial intelligence chatbots (ChatGPT 4.0, Gemini 2.5, and Microsoft Copilot) in the radiographic evaluation of jaw lesions on panoramic images with different densities (mixed, radiolucent, and radiopaque). Methods: 120 panoramic radiographs showing jaw lesions with varying radiographic appearances were independently analyzed using three artificial intelligence chatbot systems. Each model was provided with the same single-round prompt and a standardized diagnostic scoring framework encompassing lesion structure, configuration, border characteristics, morphology, relationship with teeth, effects on adjacent structures, biological behavior indicators, and total diagnostic scores. Descriptive statistics were reported as mean ± standard deviation and median (minimum-maximum). Differences between LLM scores were analyzed using the Kruskal-Wallis test, followed by Bonferroni-corrected post hoc comparisons. The statistical significance level was set at p < 0.05. Results: Significant differences were observed among the LLMs across multiple diagnostic categories, including lesion structure, configuration, border characteristics, and total scores (p < 0.05). Gemini achieved the highest total scores in radiolucent (11.49 ± 4.97) and mixed lesions (9.01 ± 5.78), whereas ChatGPT showed slightly higher performance in radiopaque lesions (10.93 ± 2.88). Copilot demon… | F55: Çelik Özen, Duygu; Özen, Okan; Göktürk, Utku Tuğberk; Solak, Hamzahan; Duman, Şuayip Burak | G55: 2026 | H55: Diagnostics (Basel, Switzerland) | I55: 10.3390/diagnostics16132064 | J55: 42449845.0 | K55: Journal article (original research) | L55: English | M55: Oral & maxillofacial radiology | N55: DOAJ; Europe PMC; PubMed/MEDLINE; Semantic Scholar | O55: EXCLUDE | P55: E3 | Q55: panoramic radiograph jaw lesion interpretation | R55: EXCLUDE | S55: E3 | T55: panoramic radiograph jaw lesion interpretation | U55: =IF(AND(O55=R55,O55<>"UNSURE"),"Agree","Conflict/Unsure") -> Agree | Y55: 0.362 | Z55: 718 | AA55: No | AD55: EXCLUDE | AE55: E3 | AF55: R1 = R2
A56: LLMDENT-0022 | B56: 55 | C56: calibration | D56: Zero-shot detection of apical periodontitis on periapical radiographs using multimodal large language models: diagnostic accuracy and error patterns. | E56: Abstract Background The present study evaluated the diagnostic performance of three general-purpose multimodal large language models (MLLMs)—Claude 4.5 Sonnet, GPT-5.2 Thinking, and Gemini 3.0 Pro—in detecting apical periodontitis on periapical radiographs. Methods One hundred twenty periapical radiographs were included (60 apical periodontitis–positive and 60 healthy), retrieved from routine clinical records at a university dental clinic. Teeth with root canal fillings and radiographs showing metallic artifacts were excluded to minimize superimposition in the apical region. Two experienced clinicians independently assessed all images to establish the reference standard based on two-dimensional periapical radiographic interpretation without CBCT confirmation. Disagreements were resolved by consensus, and interobserver agreement was high (Cohen’s κ = 0.88). The same coded images were subsequently evaluated by the three MLLMs in separate sessions using a standardized prompt, without any example or training images. Model outputs were restricted to binary “present/absent” responses. Accuracy, sensitivity, specificity, positive predictive value (PPV), and negative predictive value (NPV) were calculated. Differences among models were analyzed using Cochran’s Q test (α = 0.05), followed by Bonferroni-adjusted McNemar tests. Results Gemini 3.0 Pro achieved the highest overall accuracy (71.67%). This performance was significantly superior to that of Claude 4.5 Sonnet (Bonferroni-adjus… | F56: Adıgüzel, Mehmet; Özeken, Furkan; Özeken, Tuba | G56: 2026 | H56: BMC oral health | I56: 10.1186/s12903-026-09026-7 | J56: 42351136.0 | K56: Journal article (original research) | L56: English | M56: Endodontics; Periodontology; Restorative dentistry / cariology; Oral & maxillofacial radiology | N56: Crossref; DOAJ; Europe PMC; PubMed/MEDLINE; Semantic Scholar | O56: EXCLUDE | P56: E3 | Q56: periapical radiograph apical periodontitis detection | R56: EXCLUDE | S56: E3 | T56: periapical radiograph apical periodontitis detection | U56: =IF(AND(O56=R56,O56<>"UNSURE"),"Agree","Conflict/Unsure") -> Agree | Y56: 0.176 | Z56: 1366 | AA56: No | AD56: EXCLUDE | AE56: E3 | AF56: R1 = R2
A57: LLMDENT-0071 | B57: 56 | C57: calibration | D57: Human versus artificial intelligence in oral pathology diagnosis: a comparative study of ChatGPT, Grok, and MANUS. | E57: Artificial intelligence (AI) integration in diagnostic medicine has advanced accuracy and efficiency, particularly in pathology. This study assessed the diagnostic performance of three large language models (LLMs)—ChatGPT (GPT-4-turbo), Grok (xAI), and MANUS—in interpreting histopathology slides of oral lesions. A comparative diagnostic study was conducted using 100 high-resolution slides representing diverse oral pathologies. Images were sourced from a validated textbook and reviewed by two board-certified oral pathologists who provided consensus diagnoses. Each slide was analysed twice by the three AI models using standardized prompts. Diagnostic accuracy, intra-model consistency, inter-model concordance, and agreement with human experts were evaluated using descriptive statistics, Cohen’s kappa, McNemar’s test, and chi-square analysis. All AI models demonstrated high diagnostic accuracy. In the second round, Grok achieved the highest accuracy (97%), followed by MANUS (96%) and ChatGPT (94%). ChatGPT showed the highest intra-model consistency (κ = 0.918), while MANUS and Grok displayed substantial agreement (κ = 0.790 and 0.740). Expert pathologists achieved 98% accuracy. Comparisons between AI models and human diagnoses showed moderate to substantial agreement, with MANUS most aligned with experts. Most misclassifications occurred in histologically ambiguous cases, with no significant differences between AI models. Multimodal LLMs demonstrated strong diagnostic capabilitie… | F57: Alshammari, Abdullah F; Madfa, Ahmed A; Anazi, Bassam Ali | G57: 2026 | H57: Scientific reports | I57: 10.1038/s41598-026-40792-0 | J57: 41735394.0 | K57: Journal article (original research) | L57: English | M57: Oral medicine / oral pathology | N57: DOAJ; Europe PMC; PubMed/MEDLINE; Semantic Scholar | O57: EXCLUDE | P57: E3 | Q57: histopathology slide diagnosis oral lesions | R57: EXCLUDE | S57: E3 | T57: oral histopathology slide diagnosis | U57: =IF(AND(O57=R57,O57<>"UNSURE"),"Agree","Conflict/Unsure") -> Agree | Y57: 0.307 | Z57: 844 | AA57: No | AD57: EXCLUDE | AE57: E3 | AF57: R1 = R2
A58: LLMDENT-0036 | B58: 57 | C58: calibration | D58: Artificial Intelligence-assisted Periapical Radiographic Assessment: Lesion Detection, Endodontic Complication Analysis, and Review of Clinical Treatment Recommendations. | E58: INTRODUCTION: Artificial intelligence (AI) systems are increasingly used in dental radiology to support endodontic diagnosis. However, their diagnostic reliability across different clinical categories remains unclear. This study compared 3 vision-language AI models (ChatGPT-5 Plus, Gemini 2.5 Pro, and Copilot Pro) with expert endodontists by assessing sensitivity, specificity, overall diagnostic agreement, and Youden's Index across multiple endodontic conditions. METHODS: This retrospective diagnostic accuracy study evaluated the relationship between periapical radiographs and treatment decisions, procedural complications, and lesion detection. Expert endodontists served as the gold standard of reference. Diagnostic categories included primary treatment selection, nonsurgical retreatment, final treatment decisions, perforation, underfilling, overfilling, broken file, calcification, and periapical lesion detection. RESULTS: There was an almost perfect agreement between the endodontists (κ = 0.95). Gemini 2.5 Pro demonstrated the highest diagnostic accuracy, particularly in periapical lesion detection (sensitivity 100%, specificity 88%), while ChatGPT-5 Plus showed similarly strong performance in treatment selection. Copilot Pro exhibited markedly low sensitivity for complications such as perforation and instrument fracture. Kappa values for preoperative and postoperative treatment decisions were high for Gemini and ChatGPT-5 Plus, but low for Copilot Pro. The Friedman test con… | F58: Akyüz, İpek Eraslan; Kıvırcık, Beyza Ezgi; Aslan, Tuğrul | G58: 2026 | H58: Journal of endodontics | I58: 10.1016/j.joen.2026.04.008 | J58: 42019676.0 | K58: Review (narrative) | L58: English | M58: Endodontics; Oral & maxillofacial radiology | N58: Europe PMC; PubMed/MEDLINE; Semantic Scholar | O58: EXCLUDE | P58: E3 | Q58: periapical radiograph diagnosis and treatment decisions | R58: EXCLUDE | S58: E3 | T58: periapical radiograph assessment and treatment decisions | U58: =IF(AND(O58=R58,O58<>"UNSURE"),"Agree","Conflict/Unsure") -> Agree | Y58: 0.17 | Z58: 1395 | AA58: No | AD58: EXCLUDE | AE58: E3 | AF58: R1 = R2
A59: LLMDENT-0568 | B59: 58 | C59: calibration | D59: A benchmark multimodal oro-dental dataset for large vision-language models. | E59: The advancement of artificial intelligence in oral healthcare relies on the availability of large-scale multimodal datasets that capture the complexity of clinical practice. In this paper, we present a comprehensive multimodal dataset, comprising 8775 dental checkups from 4800 patients collected over eight years (2018-2025), with patients ranging from 10 to 90 years of age. The dataset includes 50000 intraoral photographs, 8056 radiographs, and detailed textual records, including diagnoses, treatment plans, and follow-up notes. The data were collected under standard ethical guidelines and annotated for benchmarking. To demonstrate its utility, we fine-tuned state-of-the-art large vision-language models, Qwen-VL 3B and 7B, and evaluated them on two tasks: classification of six oro-dental anomalies and generation of complete diagnostic reports from multimodal inputs. We compared the fine-tuned models with their base counterparts and GPT-4o. The fine-tuned models achieved substantial gains over these baselines, validating the dataset and underscoring its effectiveness in advancing AI-driven oro-dental healthcare solutions. The dataset is publicly available, providing an essential resource for future research in AI dentistry. | F59: Lv, Haoxin; Haq, Ijazul; Du, Jin; Ma, Jiaxin; Zhu, Binnian; Dang, Xiaobing; Liang, Chaoan; Du, Ruxu; Zhang, Yingjie; Saqib, Muhammad | G59: 2026 | H59: Scientific data | I59: 10.1038/s41597-026-07342-9 | J59: 42062311.0 | K59: Journal article (original research) | L59: English | M59: Oral & maxillofacial radiology | N59: Europe PMC; PubMed/MEDLINE; Semantic Scholar; arXiv | O59: EXCLUDE | P59: E3 | Q59: multimodal dental dataset; diagnostic classification and reports | R59: EXCLUDE | S59: E3 | T59: multimodal dataset; fine-tuned VLM diagnostic reports; GPT-4o baseline | U59: =IF(AND(O59=R59,O59<>"UNSURE"),"Agree","Conflict/Unsure") -> Agree | Y59: 0.033 | Z59: 2019 | AA59: No | AD59: EXCLUDE | AE59: E3 | AF59: R1 = R2
A60: LLMDENT-1681 | B60: 59 | C60: calibration | D60: Assessing the quality of AI information from ChatGPT regarding oral surgery, preventive dentistry, and oral cancer: An exploration study. | E60: AIM: Evaluation of the quality of dental information produced by the ChatGPT artificial intelligence language model within the context of oral surgery, preventive dentistry, and oral cancer. METHODOLOGY: This study adopted quantitative methods approach. The experts prepared 50 questions (including dimensions of, risk factors, preventive measures, diagnostic methods, and treatment options) that would be presented to ChatGPT, and its responses were rated for their accuracy, completeness, relevance, clarity or comprehensibility, and possible risks using a standardized rubric. To carry out the assessment of the responses by ChatGPT, a standardized scoring rubric was used. Evaluation process included feedback concerning the strengths, weaknesses, and potential areas of improvement in the responses provided by ChatGPT. RESULTS: While achieving the highest score for preventive dentistry at 4.3/5 and being able to communicate the complex information coherently, the tool showed lower accuracy for oral surgery and oral cancer, scoring 3.9/5 and 3.6/5, respectively, with several gaps for post-operative instructions, personalized risk assessments, and specialized diagnostic methods. Potential risks, such as a lack of individualized advice, were shown in 53% of the oral cancer and in 40% of the oral surgery. While showing promise in some domains, ChatGPT had important limitations in specialized areas that require nuanced expertise. CONCLUSION: The findings point to the need for profession… | F60: Alsayed, Arwa A; Aldajani, Mariam B; Aljohani, Marwan H; Alamri, Hamdan; Alwadi, Maram A; Alshammari, Bodor Z; Alshammari, Falah R | G60: 2024 | H60: The Saudi dental journal | I60: 10.1016/j.sdentj.2024.09.009 | J60: 39619711.0 | K60: Journal article (original research) | L60: English | M60: Oral & maxillofacial surgery; Oral medicine / oral pathology; Preventive dentistry / dental public health | N60: Amass BiomedCore (connector); Consensus (connector); DOAJ; Europe PMC; PubMed/MEDLINE; Semantic Scholar | O60: INCLUDE | P60: - | Q60: ChatGPT oral surgery prevention oral cancer; accuracy completeness risks; audience unclear | R60: INCLUDE | S60: - | T60: ChatGPT oral surgery prevention oral cancer info; accuracy completeness risks | U60: =IF(AND(O60=R60,O60<>"UNSURE"),"Agree","Conflict/Unsure") -> Agree | Y60: 0.675 | Z60: 317 | AA60: No | AD60: INCLUDE | AE60: - | AF60: R1 = R2
A61: LLMDENT-1070 | B61: 60 | C61: calibration | D61: Integrating Artificial Intelligence into Orthodontic Education: A Systematic Review and Meta-Analysis of Clinical Teaching Application. | E61: Background/Objectives : Artificial intelligence (AI) is rapidly emerging as a transformative force in healthcare education, including orthodontics. This systematic review and meta-analysis aimed to evaluate the integration of AI into orthodontic training programs, focusing on its effectiveness in improving diagnostic accuracy, learner engagement, and the perceived quality of AI-generated educational content. Materials and Methods : A comprehensive literature search was conducted across PubMed, Scopus, Web of Science, and Embase through May 2025. Eligible studies involved AI-assisted educational interventions in orthodontics. A mixed-methods approach was applied, combining meta-analysis and narrative synthesis based on data availability and consistency. Results : Seven studies involving 1101 participants-including orthodontic students, clinicians, faculty, and program directors-were included. AI tools ranged from cephalometric landmarking platforms to ChatGPT-based learning modules. A fixed-effects meta-analysis using two studies yielded a pooled Global Quality Scale (GQS) score of 3.69 (95% CI: 3.58-3.80), indicating moderate perceived quality of AI-generated content (I 2 = 64.5%). Due to methodological heterogeneity and limited statistical reporting in most studies, a narrative synthesis was used to summarize additional outcomes. AI tools enhanced diagnostic skills, learner autonomy, and perceived satisfaction, particularly among students and junior faculty. However, barrier… | F61: Ardila, Carlos M; Pineda-Vélez, Eliana; Vivares Builes, Anny Marcela | G61: 2025 | H61: Journal of clinical medicine | I61: 10.3390/jcm14155487 | J61: 40807106.0 | K61: Systematic review / meta-analysis | L61: English | M61: Orthodontics; Dental education / exams | N61: Europe PMC; PubMed/MEDLINE; Semantic Scholar | O61: EXCLUDE | P61: E3 | Q61: SR/MA AI in orthodontic education | R61: EXCLUDE | S61: E5 | T61: systematic review AI orthodontic education | U61: =IF(AND(O61=R61,O61<>"UNSURE"),"Agree","Conflict/Unsure") -> Agree | Y61: 0.115 | Z61: 1683 | AA61: No | AD61: EXCLUDE | AE61: E5 | AF61: R1 = R2
A62: LLMDENT-0359 | B62: 61 | C62: batch_01 | D62: Large Language Models for Readable and Clinically Complete Wisdom Tooth Consent Forms: A Comparative Study | F62: Sonali Halder | G62: 2026 | H62: International Journal of Applied Dental Sciences | I62: 10.22271/oral.2026.v12.i6a.2412 | K62: Journal article (original research) | L62: English (automatically detected) | M62: Oral & maxillofacial surgery | N62: Semantic Scholar | O62: INCLUDE | P62: - | Q62: LLM-generated wisdom tooth consent forms; completeness; no abstract | R62: INCLUDE | S62: - | T62: no abstract; LLM wisdom tooth consent forms; clinical completeness | U62: =IF(AND(O62=R62,O62<>"UNSURE"),"Agree","Conflict/Unsure") -> Agree | Y62: 0.303 | Z62: 857 | AA62: No | AD62: INCLUDE | AE62: - | AF62: R1 = R2
A63: LLMDENT-1022 | B63: 62 | C63: batch_01 | D63: The Role of ChatGPT in Modern Oral and Maxillofacial Surgery-A Narrative Review | E63: The ChatGPT, a specialized version of the Generative Pretrained Transformer 4 (GPT-4) developed by OpenAI, is a significant advancement in Large Language Models (LLMs). Integrating AI-powered ChatGPT into oral and maxillofacial surgery represents a transformative change in healthcare, improving diagnostics, treatment planning, patient communication, and surgical training. Its rapid analysis of extensive databases ensures precise, personalized diagnosis and treatment strategies, reducing risks and enhancing patient outcomes. ChatGPT enables virtual consultations, educates patients, and acts as a real-time surgical assistant during procedures, while AI-driven techniques simultaneously improve the skills of aspiring surgeons. | F63: A. D.; Shobha E. S.; Vinod Rangan; Vipul M. Naik; Kaushik; Dheeraj N. Shet; Yashas Raj | G63: 2025 | H63: International Journal For Multidisciplinary Research | I63: 10.36948/ijfmr.2025.v07i01.32967 | K63: Review (narrative) | L63: English (automatically detected) | M63: Oral & maxillofacial surgery | N63: Semantic Scholar | O63: EXCLUDE | P63: E5 | Q63: narrative review ChatGPT in OMFS | R63: EXCLUDE | S63: E5 | T63: narrative review ChatGPT in OMFS | U63: =IF(AND(O63=R63,O63<>"UNSURE"),"Agree","Conflict/Unsure") -> Agree | Y63: 0.225 | Z63: 1143 | AA63: No | AD63: EXCLUDE | AE63: E5 | AF63: R1 = R2
A64: LLMDENT-1894 | B64: 63 | C64: batch_01 | D64: Cautionary note: Chatbots generate fictitious references on the topics related to oral pathology | E64: Background: While chatbots such as Chat Generative Pre-Trained Transformer (ChatGPT) and BARD have gained significant popularity in aiding researchers in crafting scientific articles, concerns persist, particularly regarding their accuracy in generating references. This is especially pronounced in specialized fields like oral pathology, where precision is paramount. Methods: We conducted a comprehensive comparison between ChatGPT and BARD in the context of generating references for five frequently researched topics within oral pathology. To assess accuracy, we subjected fifty references generated by each model to rigorous evaluation based on multiple parameters. The validation process involved meticulous cross-referencing across prominent scientific databases. Results: ChatGPT demonstrated a reference accuracy of only 10 %, revealing notable inconsistencies across various parameters. Conversely, BARD exhibited a substantial 88 % inaccuracy rate in total references, with only 4 references managing to provide the correct title. Notably, the DOI led to the accurate manuscript in only 12 % (9) of references generated by ChatGPT and 4 % (8) of references from BARD. Analysis indicated significantly better performance by the ChatGPT in comparison to BARD (p < 0.05). Conclusion: Prudence is advised when incorporating references generated by ChatGPT and BARD on topics related to oral pathology. There is a pressing need for publishers to fortify systems for scrutinizing references and … | F64: G. Sarode; Shruti Singh; S. Sarode | G64: 2024 | H64: Oral Oncology Reports | I64: 10.1016/j.oor.2024.100168 | K64: Journal article (original research) | L64: English (automatically detected) | M64: Oral medicine / oral pathology | N64: DOAJ; Semantic Scholar | O64: EXCLUDE | P64: E2 | Q64: ChatGPT/Bard reference generation for research writing | R64: EXCLUDE | S64: E3 | T64: fabricated references oral pathology; research/academic use | U64: =IF(AND(O64=R64,O64<>"UNSURE"),"Agree","Conflict/Unsure") -> Agree | Y64: 0.356 | Z64: 732 | AA64: No | AD64: EXCLUDE | AE64: E2 | AF64: R1 = R2
A65: LLMDENT-0424 | B65: 64 | C65: batch_01 | D65: Comparative Evaluation of Vision-Language Models for Detecting and Localizing Dental Lesions from Intraoral Images. | E65: To assess the efficiency of vision-language models in detecting and classifying carious and non-carious lesions from intraoral photo imaging. A dataset of 172 annotated images were classified for microcavitation, cavitated lesions, staining, calculus, and non-carious lesions. Florence-2, PaLI-Gemma, and YOLOv8 models were trained on the dataset and model performance. The dataset was divided into 80:10:10 split, and the model performance was evaluated using mean average precision (mAP), mAP50-95, class-specific precision and recall. YOLOv8 outperformed the vision-language models, achieving a mean average precision (mAP) of 37% with a precision of 42.3% (with 100% for cavitation detection) and 31.3% recall. PaLI-Gemma produced a recall of 13% and 21%. Florence-2 yielded a mean average precision of 10% with a precision and recall was 51% and 35%. YOLOv8 achieved the strongest overall performance. Florence-2 and PaLI-Gemma models underperformed relative to YOLOv8 despite the potential for multimodal contextual understanding, highlighting the need for larger, more diverse datasets and hybrid architectures to achieve improved performance. | F65: Jahan, Maria; Siam, Al Ibne; Pronay, Lamim Zakir; Ahmed, Saif; Mohammed, Nabeel; Dudley, James; Farook, Taseef Hasan | G65: 2026 | H65: Journal of imaging | I65: 10.3390/jimaging12010022 | J65: 41590907.0 | K65: Journal article (original research) | L65: English | M65: Oral & maxillofacial radiology | N65: Europe PMC; PubMed/MEDLINE; Semantic Scholar | O65: EXCLUDE | P65: E2 | Q65: trained vision-language models and YOLO lesion detection | R65: EXCLUDE | S65: E2 | T65: trained VLMs and YOLO on intraoral images; not chatbot | U65: =IF(AND(O65=R65,O65<>"UNSURE"),"Agree","Conflict/Unsure") -> Agree | Y65: 0.109 | Z65: 1714 | AA65: No | AD65: EXCLUDE | AE65: E2 | AF65: R1 = R2
A66: LLMDENT-1296 | B66: 65 | C66: batch_01 | D66: KokushiMD-10: Benchmark for Evaluating Large Language Models on Ten Japanese National Healthcare Licensing Examinations | E66: Recent advances in large language models (LLMs) have demonstrated notable performance in medical licensing exams. However, comprehensive evaluation of LLMs across various healthcare roles, particularly in high-stakes clinical scenarios, remains a challenge. Existing benchmarks are typically text-based, English-centric, and focus primarily on medicines, which limits their ability to assess broader healthcare knowledge and multimodal reasoning. To address these gaps, we introduce KokushiMD-10, the first multimodal benchmark constructed from ten Japanese national healthcare licensing exams. This benchmark spans multiple fields, including Medicine, Dentistry, Nursing, Pharmacy, and allied health professions. It contains over 11588 real exam questions, incorporating clinical images and expert-annotated rationales to evaluate both textual and visual reasoning. We benchmark over 30 state-of-the-art LLMs, including GPT-4o, Claude 3.5, and Gemini, across both text and image-based settings. Despite promising results, no model consistently meets passing thresholds across domains, highlighting the ongoing challenges in medical AI. KokushiMD-10 provides a comprehensive and linguistically grounded resource for evaluating and advancing reasoning-centric medical AI across multilingual and multimodal clinical tasks. | F66: Jun-Yu Liu; Kai Yan; Tian-Yang Wang; Qian Niu; M. Nagai-Tanima; T. Aoyama | G66: 2025 | H66: Agentic AI/CREATE/Clinical MLLMs@MICCAI | I66: 10.48550/arxiv.2506.11114 | K66: Journal article (original research) | L66: English (automatically detected) | M66: Dental education / exams; General dentistry / cross-specialty | N66: Semantic Scholar; arXiv | O66: EXCLUDE | P66: E3 | Q66: licensing exam benchmark | R66: EXCLUDE | S66: E3 | T66: licensing exam benchmark incl. dentistry | U66: =IF(AND(O66=R66,O66<>"UNSURE"),"Agree","Conflict/Unsure") -> Agree | Y66: 0.038 | Z66: 2007 | AA66: No | AD66: EXCLUDE | AE66: E3 | AF66: R1 = R2
A67: LLMDENT-0059 | B67: 66 | C67: batch_01 | D67: Guideline Concordance of Antibiotic Recommendations From Large Language Models in Dentistry: A Vignette-Based Evaluation in Georgian and English | E67: Introduction: Inappropriate antibiotic prescribing in dentistry is a recognised stewardship concern.Large language models (LLMs) are readily accessible sources of prescribing information, but dental evaluations have been conducted almost entirely in English.We compared the guideline concordance of matched Georgian and English LLM recommendations for common dental presentations in a setting in which we could identify no national dental antibiotic prescribing guideline.Materials and methods: In this preregistered vignette study, 20 standardised scenarios (10 antibioticindicated, 10 not) were submitted in Georgian and English to the free-tier interfaces of Claude (Anthropic, San Francisco, USA), ChatGPT (OpenAI, San Francisco, USA) and Gemini (Google LLC, Mountain View, USA) on three occasions (360 responses).Responses were normalised, blinded to system and run, and coded by two dentists against a key based on Scottish Dental Clinical Effectiveness Programme (SDCEP), American Dental Association (ADA) 2019 and American Heart Association (AHA) 2021 guidance on five domains: decision to prescribe, agent, dose and frequency, duration, and referral advice.Disagreements were adjudicated and the regimen domains were re-scored under clarified rules.The primary outcome was full concordance on all applicable domains in the first run, compared across 60 matched scenario-system pairs with the exact McNemar test.Results: Full concordance was 57/60 (95.0%, 95% CI 86.3 to 98.3) for English and… | G67: 2026 | H67: Cureus | I67: 10.7759/cureus.117183 | K67: Journal article (original research) | L67: English (automatically detected) | M67: Dental pharmacology / anesthesia | N67: Semantic Scholar | O67: EXCLUDE | P67: E3 | Q67: antibiotic prescribing vignettes for dentists | R67: EXCLUDE | S67: E3 | T67: antibiotic prescribing vignettes; guideline concordance for dentists | U67: =IF(AND(O67=R67,O67<>"UNSURE"),"Agree","Conflict/Unsure") -> Agree | Y67: 0.428 | Z67: 578 | AA67: No | AD67: EXCLUDE | AE67: E3 | AF67: R1 = R2
A68: LLMDENT-0392 | B68: 67 | C68: batch_01 | D68: Evaluation of GPT-5, a Large Language Model, in Replicating German Clinical Practice Guideline Recommendations in Oral Oncology: A Cross-Sectional Concordance Study. | E68: BACKGROUND: Artificial intelligence (AI) technologies, particularly large language models (LLMs) such as ChatGPT, are increasingly utilised in medical education and clinical information retrieval. Nevertheless, their capacity to accurately reproduce recommendations from established clinical practice guidelines (CPGs) has not been thoroughly examined. The present study evaluated the concordance between responses generated by GPT-5 and recommendations contained in German CPGs addressing oral potentially malignant disorders (OPMDs) and oral carcinomas (OCs). METHODS: A cross-sectional analytical comparison was performed between GPT-5 outputs and German CPG recommendations available as of October 2025. Individual guideline statements were entered verbatim into GPT-5, which was asked to confirm or reject the statements. To assess methodological robustness, inverted versions of the same statements were additionally tested. GPT-5 was accessed through the free version without internet connectivity to ensure that responses originated solely from the model's internal training data. Accuracy was defined as the proportion of correctly classified statements. Concordance between guideline content and model responses was quantified using Cohen's 𝝹. RESULTS: Two German CPGs comprising 111 recommendations were included: the S2k guideline for OPMDs (15 recommendations) and the S3 guideline for OCs (96 recommendations). GPT-5 correctly affirmed all authentic recommendations and rejected all inv… | F68: Hirsch, Julius; Subbalekha, Keskanya; Tangmanee, Chatpong; Stoll, Christian; Pitak-Arnnop, Poramate | G68: 2026 | H68: Journal of oral pathology & medicine : official publication of the International Association of Oral Pathologists and the American Academy of Oral Pathology | I68: 10.1111/jop.70140 | J68: 41967843.0 | K68: Journal article (original research) | L68: English | M68: Oral medicine / oral pathology; Dental education / exams | N68: Crossref; Europe PMC; PubMed/MEDLINE; Semantic Scholar | O68: EXCLUDE | P68: E3 | Q68: GPT-5 guideline statement concordance oral oncology | R68: EXCLUDE | S68: E3 | T68: GPT-5 confirming German oral oncology guideline statements | U68: =IF(AND(O68=R68,O68<>"UNSURE"),"Agree","Conflict/Unsure") -> Agree | Y68: 0.407 | Z68: 616 | AA68: No | AD68: EXCLUDE | AE68: E3 | AF68: R1 = R2
A69: LLMDENT-1433 | B69: 68 | C69: batch_01 | D69: Assessment of the Performance of Large Language Models ChatGPT, ChatGPT Plus, Gemini, and Microsoft Copilot in Responding to Oral and Maxillofacial Radiology Questions from the Turkish Dentistry Specialty Entrance Exam | E69: Microsoft Copilot Büyük Dil Modellerinin Türkiye'deki Diş Hekimliği Uzmanlık Eğitimi Giriş Sınavı'nda Sorulan Ağız, Diş ve Çene Radyolojisi Sorularını Cevaplama Performanslarının Değerlendirilmesi Assessment of the Performance of Large Language Models ChatGPT, ChatGPT Plus, Gemini, and Microsoft Copilot in Responding to Oral and Maxillofacial Radiology Questions from the Turkish Dentistry Specialty Entrance Exam | F69: Peker, Ramazan Berkay | G69: 2025 | H69: Yeditepe Dental Journal | I69: 10.5505/yeditepe.2025.93265 | K69: Journal article (original research) | L69: English (automatically detected) | M69: Oral & maxillofacial surgery | N69: Crossref; Semantic Scholar | O69: EXCLUDE | P69: E3 | Q69: specialty entrance exam radiology questions | R69: EXCLUDE | S69: E3 | T69: specialty entrance exam radiology questions | U69: =IF(AND(O69=R69,O69<>"UNSURE"),"Agree","Conflict/Unsure") -> Agree | Y69: 0.329 | Z69: 791 | AA69: No | AD69: EXCLUDE | AE69: E3 | AF69: R1 = R2
A70: LLMDENT-1564 | B70: 69 | C70: batch_01 | D70: Reading Smiles: Proxy Bias in Foundation Models for Facial Emotion Recognition | E70: Foundation Models, and, in particular, Vision-Language Models, are reshaping Affective Computing by enabling strong zero-shot facial-emotion recognition. Yet their decisions often hinge on so–called proxy bias: the unintended use of salient but non-causal cues (e.g. visible teeth) as shortcuts for emotion inference. We benchmark ten Vision-Language Models of different scales on a teeth-annotated subset of AffectNet and observe consistent drops in performance whenever teeth are not visible, confirming the presence of such shortcuts. Focusing on the top-performing GPT-4o, we employ a structured-prompt “introspection” that forces the model to report intermediate facial attributes. Regression analysis shows that features like eyebrow position and mouth openness explain over 70 % of GPT-4o’s continuous valence–arousal outputs, indicating a systematic yet shortcut-driven mapping from perception to affect. While this internal consistency highlights an emergent capability of foundation models, the same mechanism amplifies the risks of bias and fairness violations in high-stakes applications such as mental health monitoring or educational feedback. Our findings motivate bias-aware evaluation protocols and lightweight attribution tools before deploying Vision-Language Model-based affective systems in real-world applications. | F70: Iosif Tsangko; Andreas Triantafyllopoulos; Adem Abdelmoula; Adria Mallol-Ragolta; Björn W. Schuller | G70: 2025 | H70: IEEE Access | I70: 10.1109/access.2025.3636968 | K70: Journal article (original research) | L70: English (automatically detected) | M70: General dentistry / cross-specialty | N70: Semantic Scholar; arXiv | O70: EXCLUDE | P70: E1 | Q70: facial emotion recognition bias; not dental | R70: EXCLUDE | S70: E1 | T70: facial emotion recognition VLM bias; not dental care | U70: =IF(AND(O70=R70,O70<>"UNSURE"),"Agree","Conflict/Unsure") -> Agree | Y70: 0.069 | Z70: 1901 | AA70: No | AD70: EXCLUDE | AE70: E1 | AF70: R1 = R2
A71: LLMDENT-0327 | B71: 70 | C71: batch_01 | D71: The Performance of Large Language Models on Antibiotic Prophylaxis for Endodontic Treatments. | E71: This study compared the accuracy and repeatability of responses generated by three advanced language models (ChatGPT-4, Gemini, and DeepSeek) in determining the necessity and appropriate regimen of antibiotic prophylaxis in endodontic treatment. 15 questions on the basis of guidance published by the European Society of Endodontics in 2018 were developed and presented to each model by three different users, three times per day over 10 consecutive days. Accuracy was evaluated for individual questions and overall performance, and repeatability across days and times was statistically analysed. All models consistently provided correct responses for patients with penicillin allergy and those with a history of infective endocarditis. Significant differences were observed in responses regarding joint prosthesis, high-dose radiation to the jaws, bypass surgery history, and controlled diabetes, although overall accuracy did not differ significantly among models. These findings highlight the potential clinical value of the models, but their responses must be verified before clinical use. | F71: Goker Kamali, Selin; Imamoglu, Yaren Tuana | G71: 2026 | H71: Australian endodontic journal : the journal of the Australian Society of Endodontology Inc | I71: 10.1111/aej.70086 | J71: 42003273.0 | K71: Journal article (original research) | L71: English | M71: Endodontics; Dental pharmacology / anesthesia | N71: Crossref; Europe PMC; PubMed/MEDLINE; Semantic Scholar | O71: EXCLUDE | P71: E3 | Q71: antibiotic prophylaxis guideline questions; prescribing support | R71: EXCLUDE | S71: E3 | T71: antibiotic prophylaxis guidance questions for endodontic clinicians | U71: =IF(AND(O71=R71,O71<>"UNSURE"),"Agree","Conflict/Unsure") -> Agree | Y71: 0.52 | Z71: 445 | AA71: No | AD71: EXCLUDE | AE71: E3 | AF71: R1 = R2
A72: LLMDENT-0663 | B72: 71 | C72: batch_01 | D72: Artificial Intelligence Chatbots' Performance on Dental Trauma Case-based Queries: Examining the Effect of Prompt and Content Engineering. | E72: INTRODUCTION: Traumatic dental injuries (TDIs) require prompt and accurate guidance, yet little is known about how the prompting influences the quality of artificial intelligence (AI) chatbot responses in these situations. METHODS: Four dental trauma scenarios were developed by expert endodontists. For each scenario, a series of questions was posed to 4 AI chatbots (Claude Sonnet 3.5, Microsoft Copilot, GPT-4, Gemini Pro 2.5) using 2 approaches: unprompted layperson phrasing (n = 10) and endodontist's prompts referencing International Association of Dental Traumatology guidelines (n = 10). Responses were independently evaluated by 2 raters for validity, completeness, and relevance using a 5-point ordinal scale. RESULTS: Scores (n = 1920) of responses to endodontist questions were associated with significantly higher odds of receiving superior ratings across all 3 domains: validity (odds ratio [OR] = 1.82; 95% confidence interval [CI]: 1.35-2.38; P < .001); completeness (OR = 2.50; 95% CI: 1.85-3.33; P < .001) and relevance (OR = 2.94; 95% CI: 2.04-4.17; P < .001). When a threshold-based acceptability (score ≥4) was applied, responses to endodontist queries were more often acceptable in criterion-based as well as overall analyses (P < .05). CONCLUSIONS: The quality of AI chatbot guidance in TDIs is significantly associated with how questions are asked. While clinically structured prompts yield more reliable responses, most patients facing dental trauma are unlikely to formulat… | F72: Ourang, Seyed AmirHossein; Kahler, Bill; Ha, William Nguyen; Jafari, Bahare; Zahedrozegar, Samira; Nosrat, Ali | G72: 2026 | H72: Journal of endodontics | I72: 10.1016/j.joen.2026.05.010 | J72: 42217615.0 | K72: Journal article (original research) | L72: English | M72: Endodontics; Dental traumatology / emergencies | N72: Amass BiomedCore (connector); Europe PMC; PubMed/MEDLINE; Semantic Scholar | O72: INCLUDE | P72: - | Q72: dental trauma scenarios; layperson vs endodontist prompts; 4 chatbots; validity completeness | R72: INCLUDE | S72: - | T72: dental trauma scenarios; layperson phrasing; four chatbots; validity completeness | U72: =IF(AND(O72=R72,O72<>"UNSURE"),"Agree","Conflict/Unsure") -> Agree | Y72: 0.764 | Z72: 254 | AA72: No | AD72: INCLUDE | AE72: - | AF72: R1 = R2
A73: LLMDENT-0956 | B73: 72 | C73: batch_01 | D73: High-Fidelity Synthesis of Temporomandibular Joint Cone-Beam Computed Tomography Images via Latent Diffusion Models. | E73: Background : The development of robust artificial intelligence (AI) models for diagnosing Temporomandibular Disorders (TMDs) is severely constrained by data scarcity and patient privacy regulations. Cone-beam computed tomography (CBCT), the gold standard for assessing osseous changes in the temporomandibular joint (TMJ), inherently contains sensitive biometric facial features, making de-identification difficult without losing critical anatomical information. This study aims to develop and evaluate TMJCTGenerator, a specialized latent diffusion model (LDM) framework designed to synthesize high-fidelity, diverse, and anonymous TMJ CBCT images. We hypothesize that this LDM approach can achieve superior anatomical fidelity and diversity compared to traditional generative adversarial network (GAN)- and variational autoencoder (VAE)-based methods, specifically in capturing fine osseous details within sagittal and coronal views of the mandibular condyle. Methods : A training dataset comprising 348 anonymized CBCT volumes was obtained in this retrospective comparative study to extract high-resolution sagittal and coronal regions of interest of the mandibular condyle. An independent test set of 39 anonymized CBCT volumes was further included. We developed a class-conditional LDM that integrates a pre-trained VAE for perceptual compression with a conditional U-Net for iterative denoising in the latent space. Performance was evaluated via qualitative anatomical fidelity assessment, Fréc… | F73: Zhang, Qinlanhui; Zheng, Yunhao; Wang, Jun | G73: 2026 | H73: Journal of clinical medicine | I73: 10.3390/jcm15093344 | J73: 42123077.0 | K73: Journal article (original research) | L73: English | M73: Oral & maxillofacial radiology; TMD / orofacial pain | N73: Europe PMC; PubMed/MEDLINE | O73: EXCLUDE | P73: E2 | Q73: latent diffusion TMJ CBCT synthesis | R73: EXCLUDE | S73: E2 | T73: latent diffusion synthesis of TMJ CBCT images | U73: =IF(AND(O73=R73,O73<>"UNSURE"),"Agree","Conflict/Unsure") -> Agree | Y73: 0.113 | Z73: 1693 | AA73: No | AD73: EXCLUDE | AE73: E2 | AF73: R1 = R2
A74: LLMDENT-1521 | B74: 73 | C74: batch_01 | D74: Performance of artificial intelligence on Turkish dental specialization exam: can ChatGPT-4.0 and gemini advanced achieve comparable results to humans? | E74: Abstract Background AI-powered chatbots have spread to various fields including dental education and clinical assistance to treatment planning. The aim of this study is to assess and compare leading AI-powered chatbot performances in dental specialization exam (DUS) administered in Turkey and compare it with the best performer of that year. Methods DUS questions for 2020 and 2021 were directed to ChatGPT-4.0 and Gemini Advanced individually. DUS questions were manually entered into AI-powered chatbot in their original form, in Turkish. The results obtained were compared with each other and the year’s best performers. Candidates who score at least 45 points on this centralized exam are deemed to have passed and are eligible to select their preferred department and institution. The data was statistically analyzed using Pearson’s chi-squared test (p < 0.05). Results ChatGPT-4.0 received 83.3% correct response rate on the 2020 exam, while Gemini Advanced received 65% correct response rate. On the 2021 exam, ChatGPT-4.0 received 80.5% correct response rate, whereas Gemini Advanced received 60.2% correct response rate. ChatGPT-4.0 outperformed Gemini Advanced in both exams (p < 0.05). AI-powered chatbots performed worse in overall score (for 2020: ChatGPT-4.0, 65,5 and Gemini Advanced, 50.1; for 2021: ChatGPT-4.0, 65,6 and Gemini Advanced, 48.6) when compared to overall scores of the best performer of that year (68.5 points for year 2020 and 72.3 points for year 2021). This poor pe… | F74: Sismanoglu, Soner; Capan, Belen Sirinoglu | G74: 2025 | H74: BMC medical education | I74: 10.1186/s12909-024-06389-9 | J74: 39930399.0 | K74: Journal article (original research) | L74: English | M74: Orthodontics; Endodontics; Periodontology; Dental education / exams | N74: Crossref; DOAJ; Europe PMC; PubMed/MEDLINE; Semantic Scholar | O74: EXCLUDE | P74: E3 | Q74: dental specialization exam | R74: EXCLUDE | S74: E3 | T74: Turkish dental specialty exam | U74: =IF(AND(O74=R74,O74<>"UNSURE"),"Agree","Conflict/Unsure") -> Agree | Y74: 0.291 | Z74: 898 | AA74: No | AD74: EXCLUDE | AE74: E3 | AF74: R1 = R2
A75: LLMDENT-1485 | B75: 74 | C75: batch_01 | D75: The Transformative Role of Artificial Intelligence in Dentistry: A Comprehensive Overview. Part 1: Fundamentals of AI, and its Contemporary Applications in Dentistry. | E75: Artificial intelligence (AI) holds immense promise in revolutionising dentistry, spanning, diagnostics, treatment planning and educational realms. This narrative review, in two parts, explores the fundamentals and the multifaceted potential of AI in dentistry. The current article explores the profound impact of AI in dentistry, encompassing diagnostic tools, treatment planning, and patient care. The Part 2 of the article delves into the potential of AI in patient education, ethics and the FDI communique on AI in dentistry. The review begins by elucidating the historical context of AI, outlining its recent widespread use in various sectors, including medicine and dentistry. The narrative delves into the fundamental concepts of AI, which entails developing machines capable of executing tasks that typically necessitate human intellect. In the biomedical realm, AI has evolved from exploring computational models to constructing systems for clinical data processing and interpretation, aiming to enhance medical/dental decision-making. The discussion delves into the pivotal role of AI models in dentistry, such as Large Language Models (LLM), Large Vision Models (LVM), and Multimodality Models (MM), revolutionizing processes from clinical documentation to treatment planning. The narrative extends to the applications of AI in dental specialties such as periodontics, endodontics, oral medicine and pathology, restorative dentistry, prosthodontics, paediatric dentistry, forensic odontolog… | F75: Samaranayake, Lakshman; Tuygunov, Nozimjon; Schwendicke, Falk; Osathanon, Thanaphum; Khurshid, Zohaib; Boymuradov, Shukhrat A; Cahyanto, Arief | G75: 2025 | H75: International dental journal | I75: 10.1016/j.identj.2025.02.005 | J75: 40074616.0 | K75: Review (narrative) | L75: English | M75: Orthodontics; Endodontics; Periodontology; Prosthodontics; Oral & maxillofacial surgery; Pediatric dentistry; Restorative dentistry / cariology; Oral medicine / oral pathology; TMD / orofacial pain; Preventive dentistry / dental public health | N75: Amass BiomedCore (connector); Europe PMC; PubMed/MEDLINE; Semantic Scholar | O75: EXCLUDE | P75: E5 | Q75: narrative review AI in dentistry | R75: EXCLUDE | S75: E5 | T75: narrative review AI in dentistry | U75: =IF(AND(O75=R75,O75<>"UNSURE"),"Agree","Conflict/Unsure") -> Agree | Y75: -0.014 | Z75: 2109 | AA75: No | AD75: EXCLUDE | AE75: E5 | AF75: R1 = R2
A76: LLMDENT-1462 | B76: 75 | C76: batch_01 | D76: A Review of ChatGPT as a Reliable Source of Scientific Information Regarding Endodontic Local Anesthesia. | E76: INTRODUCTION ChatGPT is an artificial intelligence (AI) chatbot, developed by OpenAI, that uses Deep Learning (DL) technology for information processing. The chatbot uses natural language processing (NLP) and machine learning (ML) algorithms to respond to users' questions. The purpose of this study was to review ChatGPT responses to determine if they were a reliable source of scientific information regarding local anesthesia for endodontics. MATERIALS AND METHODS Sixteen representative questions pertaining to local anesthesia for endodontics were selected. ChatGPT was asked to answer the 16 questions and provide supporting references. Each provided ChatGPT reference was evaluated for accuracy using NLM NIH.GOV(PubMed), Google Scholar, journal citations, and author citations. Peer-reviewed, evidence-based literature citations related to the initial questions were collected by the authors. The two authors independently compared the answers of the ChatGPT to the peer-reviewed, evidence-based literature using a 5-answer Likert-type scale. RESULTS ChatGPT was reliable 50% of the time when compared to the peer-reviewed, evidence-based literature. That is, ChatGPT had the same literature-based response as our peer-reviewed, evidence-based literature in 16 of the 32 questions. Of the 51 total references for Chatbot, 59% (30 of 51) had the wrong reference; 12% (6 of 51) of the references couldn't be retrieved; and 18% (9 of 51) of the references were hallucinations (made up references… | F76: Reader, Al; Drum, Melissa | G76: 2025 | H76: Journal of endodontics | I76: 10.1016/j.joen.2025.02.002 | J76: 39952316.0 | K76: Review (narrative) | L76: English | M76: Endodontics; Dental pharmacology / anesthesia | N76: Crossref; Europe PMC; PubMed/MEDLINE; Semantic Scholar | O76: INCLUDE | P76: - | Q76: ChatGPT endodontic local anesthesia questions vs literature; audience unclear; original data | R76: INCLUDE | S76: - | T76: ChatGPT endodontic local anesthesia questions; Likert vs literature; audience unclear | U76: =IF(AND(O76=R76,O76<>"UNSURE"),"Agree","Conflict/Unsure") -> Agree | Y76: 0.45 | Z76: 537 | AA76: No | AD76: INCLUDE | AE76: - | AF76: R1 = R2
A77: LLMDENT-1040 | B77: 76 | C77: batch_01 | D77: Chat Generative Pretrained Transformer-4.0's accuracy in assessing cervical vertebrae and hand-wrist maturation stages: A retrospective study. | E77: INTRODUCTION: This study aimed to evaluate the diagnostic accuracy of Chat Generative Pretrained Transformer version 4.0 (ChatGPT-4.0) in determining cervical vertebrae and hand-wrist maturation stages using cephalometric and hand-wrist radiographic films. METHODS: A retrospective analysis was conducted on 238 subjects who had cephalometric and hand-wrist radiographs taken on the same day. Each hand-wrist maturation stage was independently evaluated by 3 orthodontists using the method described by Björk and Helm, whereas cervical vertebrae maturation stages were assessed following the methodology proposed by Bacetti and coworkers. These evaluations served as the reference standard for measuring the performance of ChatGPT-4.0. The hand-wrist and cephalometric radiographs were analyzed by ChatGPT-4.0, and the results were recorded by the primary researcher. RESULTS: The model achieved its highest performance in the hand-wrist maturation stages during the RU stage, with an area under the curve (AUC) value of 0.89. However, despite high precision values in the PP3U and MP3U stages, the model exhibited low recall values, indicating that certain positive instances were missed. In other stages, particularly DP3U and MP3CAP, low precision and recall values limited classification accuracy. Regarding cervical vertebral maturation stages (CVS), the model performed best in CVS1 (AUC, 0.82; precision, 0.806), with relatively favorable AUC values observed in CVS2 (AUC, 0.77). However, its … | F77: Akpınar, Meryem; Salmanpour, Farhad | G77: 2025 | H77: American journal of orthodontics and dentofacial orthopedics : official publication of the American Association of Orthodontists, its constituent societies, and the American Board of Orthodontics | I77: 10.1016/j.ajodo.2025.08.010 | J77: 41026070.0 | K77: Journal article (original research) | L77: English | M77: Orthodontics; Oral & maxillofacial radiology | N77: Europe PMC; PubMed/MEDLINE; Semantic Scholar | O77: EXCLUDE | P77: E3 | Q77: radiograph maturation staging | R77: EXCLUDE | S77: E3 | T77: radiographic maturation stage assessment | U77: =IF(AND(O77=R77,O77<>"UNSURE"),"Agree","Conflict/Unsure") -> Agree | Y77: 0.228 | Z77: 1129 | AA77: No | AD77: EXCLUDE | AE77: E3 | AF77: R1 = R2
A78: LLMDENT-0915 | B78: 77 | C78: batch_01 | D78: Performance of large language models in early orthodontic treatment: a comparative study of ChatGPT-5.4 and deepSeek-V3.2 | E78: Large language models (LLMs) are increasingly being used by patients and dental professionals to obtain orthodontic information. However, few studies have specifically compared the performance of LLMs in answering questions related to early orthodontic treatment, an area that requires complex clinical reasoning and high-quality patient education. This study aimed to evaluate the clinical applicability of ChatGPT-5.4 and DeepSeek-V3.2 in early orthodontic treatment using a multidimensional evaluation framework. Five orthodontists developed 20 questions across five domains (age of treatment, adverse oral habits, early treatment, complications, and retention and relapse). The standard answers were derived from clinical guidelines, authoritative textbooks, and articles published in Q1 journal. Each question was submitted once to each LLMs. Responses were anonymised and independently evaluated by five blinded orthodontists. Accuracy and comprehensiveness were assessed using a five-point Likert-type framework combined with visual analogue scale (VAS)-based continuous scoring. Readability was calculated using the SMOG formula. References were cross-checked against five databases and were considered authentic when their bibliographic details corresponded to an indexed publication in at least one database. Thinking time, generation time, and word count were recorded. Inter-rater agreement was assessed using the intraclass correlation coefficient (ICC). Depending on the distribution of… | F78: Xu, Jialin; Nakamura, Masahiro; Chen, Rui; Habumugisha, Janvier; Kozaki, Gohji; Zhou, Ju; Izawa, Takashi; Kamioka, Hiroshi | G78: 2026 | H78: BMC Oral Health | I78: 10.1186/s12903-026-09662-z | K78: Journal article (original research) | L78: English (automatically detected) | M78: Orthodontics | N78: Crossref; Semantic Scholar | O78: INCLUDE | P78: - | Q78: early orthodontic treatment questions; ChatGPT vs DeepSeek; accuracy completeness | R78: INCLUDE | S78: - | T78: early orthodontic treatment questions; ChatGPT vs DeepSeek; accuracy Likert | U78: =IF(AND(O78=R78,O78<>"UNSURE"),"Agree","Conflict/Unsure") -> Agree | Y78: 0.83 | Z78: 204 | AA78: No | AD78: INCLUDE | AE78: - | AF78: R1 = R2
A79: LLMDENT-1150 | B79: 78 | C79: batch_01 | D79: Artificial intelligence as a tool for data extraction is not fully reliable compared to manual data extraction. | E79: INTRODUCTION: Data extraction for systematic reviews is a time-consuming step and prone to errors. OBJECTIVE: This study aimed to evaluate the agreement between artificial intelligence and human data extraction methods. METHODS: Studies published in seven orthodontic journals between 2019 and 2024, were retrieved and included. Fifteen data sets from each study were extracted manually and using the Microsoft Bing AI-based tool by two independent reviewers. Files in Portable Document Format were uploaded to the AI-based tool, and specific data were requested through its chat feature. The association between the data extraction methods and study characteristics was examined, and agreement was evaluated using interclass correlation and Kappa statistics. RESULTS: A total of 300 orthodontic studies were included. Slight differences between human and AI-based data extraction methods for publication years and study designs were observed, though these were not statistically significant. Minor inconsistencies were also found in the extraction of the number of trial arms and the mean age of participants per group, but these were not significant. The AI-based tool was less effective in extracting variables related to the study design (P = 0.017) and the number of centers (P < 0.001). Agreement between human and AI-based extraction methods ranged from slight (0.16) for the type of study design to moderate (0.45) for study design classification, and substantial to perfect (0.65-1.00) for m… | F79: Daraqel, Baraa; Owayda, Amer; Khan, Haris; Koletsi, Despina; Mheissen, Samer | G79: 2025 | H79: Journal of dentistry | I79: 10.1016/j.jdent.2025.105846 | J79: 40449825.0 | K79: Journal article (original research) | L79: English | M79: Orthodontics; Oral & maxillofacial surgery | N79: Europe PMC; PubMed/MEDLINE | O79: EXCLUDE | P79: E2 | Q79: Bing AI as data extraction research tool | R79: EXCLUDE | S79: E3 | T79: Bing AI for systematic review data extraction | U79: =IF(AND(O79=R79,O79<>"UNSURE"),"Agree","Conflict/Unsure") -> Agree | Y79: 0.264 | Z79: 970 | AA79: No | AD79: EXCLUDE | AE79: E2 | AF79: R1 = R2
A80: LLMDENT-0678 | B80: 79 | C80: batch_01 | D80: Evaluating AI Chatbots in Prosthodontics Education: A Quantitative MCQ-Based Assessment. | E80: PURPOSE: Prosthodontics is a specialized branch of dentistry that encompasses a wide range of dental procedures, requiring advanced knowledge and expertise for both healthcare professionals. In this study, we assessed the performance of four widely accessible chatbots, ChatGPT-5, Claude 4, Microsoft Copilot, and DeepSeek-V3, using 150 clinical scenario-based prosthodontics multiple-choice questions (MCQs). Evaluating their performance is crucial to ensure reliability. MATERIALS AND METHODS: A total of 150 questions compiled from Bootcamp in English were presented to the four chatbots. We then employed multiple evaluation criteria, such as bilingual evaluation understudy (BLEU), word error rate (WER), cosine semantic similarity, and Flesch reading ease (FRE) score, to provide a more comprehensive assessment of lexical similarity, error rate, semantic consistency, and readability. RESULTS: Among the four chatbots, Microsoft Copilot (accuracy: 74%; confidence interval [CI]: 72.2%-76.2%) and ChatGPT-5 (accuracy: 73%; CI: 71.5%-75.8%) demonstrated the best overall performance, achieving high accuracy at 95% CI. Particularly, ChatGPT-5 showed the fewest word errors (WER: 7.86 [95% CI: 6.61-9.10]) and FRE readability of FRE: 20.22 (95% CI: 16.26-24.19) compared to Microsoft Copilot. In terms of alignment with reference outputs, based on the BLEU score, Claude 4 (0.0106 [95% CI: 0.0058-0.0154]) maintained higher scores compared to other analyzed chatbots. Collectively, ChatGPT-5 prod… | F80: Patil, Shankargouda; Bybee, Samuel; Venkataiah, Venkata Suresh; Amor, Shareef; Majidi, Allahe; Bhandi, Shilpa; Licari, Frank W | G80: 2026 | H80: International journal of dentistry | I80: 10.1155/ijod/5985234 | J80: 42761247.0 | K80: Journal article (original research) | L80: English | M80: Prosthodontics; Dental education / exams | N80: Amass BiomedCore (connector); DOAJ; Europe PMC; PubMed/MEDLINE; Semantic Scholar; Wiley Scholar Gateway (connector, full text) | O80: EXCLUDE | P80: E3 | Q80: prosthodontic MCQs | R80: EXCLUDE | S80: E3 | T80: prosthodontic MCQs | U80: =IF(AND(O80=R80,O80<>"UNSURE"),"Agree","Conflict/Unsure") -> Agree | Y80: 0.497 | Z80: 476 | AA80: No | AD80: EXCLUDE | AE80: E3 | AF80: R1 = R2
A81: LLMDENT-1034 | B81: 80 | C81: batch_01 | D81: Effect of AI-based chatbots in promoting oral health awareness among rural populations. | E81: AI-based chatbots significantly improved oral health awareness among rural populations compared to traditional printed materials. The intervention group's knowledge scores increased from 8.5 to 16.7 (p < 0.001), while the control group showed a modest rise from 8.3 to 10.5. Inter-group analysis confirmed a significant knowledge gain (p < 0.001). Participants reported high satisfaction with the chatbot's personalized and user-friendly interface. Thus, AI chatbots offer a promising solution for scalable, accessible oral health education in underserved communities. | F81: Agrawal, Rohit; Khan, Asim Mustafa; Moothedath, Muhamood; V J, Reshma; Muhamood, Muhaseena; T, Shivangee | G81: 2025 | H81: Bioinformation | I81: 10.6026/973206300210827 | J81: 40636219.0 | K81: Journal article (original research) | L81: English | M81: Preventive dentistry / dental public health | N81: Amass BiomedCore (connector); Europe PMC; PubMed/MEDLINE; Semantic Scholar | O81: EXCLUDE | P81: E2 | Q81: oral health chatbot intervention; architecture unclear; knowledge outcomes | R81: EXCLUDE | S81: E2 | T81: unspecified AI chatbot intervention for awareness; knowledge scores only | U81: =IF(AND(O81=R81,O81<>"UNSURE"),"Agree","Conflict/Unsure") -> Agree | Y81: 0.241 | Z81: 1064 | AA81: No | AD81: EXCLUDE | AE81: E2 | AF81: R1 = R2
A82: LLMDENT-1682 | B82: 81 | C82: batch_01 | D82: A Large Language Model Implementing an AI Assistant in a Higher Education Setting | F82: Anna Mavroudi; G.-E. Torgersen | G82: 2024 | H82: CoPDA@AVI | K82: Journal article (original research) | L82: English (automatically detected) | M82: General dentistry / cross-specialty | N82: Semantic Scholar | O82: EXCLUDE | P82: E1 | Q82: LLM assistant in higher education; not dental | R82: EXCLUDE | S82: E1 | T82: higher education AI assistant; not dental | U82: =IF(AND(O82=R82,O82<>"UNSURE"),"Agree","Conflict/Unsure") -> Agree | Y82: 0.147 | Z82: 1508 | AA82: No | AD82: EXCLUDE | AE82: E1 | AF82: R1 = R2
A83: LLMDENT-1450 | B83: 82 | C83: batch_01 | D83: Automation Bias in Large Language Model Assisted Diagnostic Reasoning Among AI-Trained Physicians | E83: Importance: Large language models (LLMs) show promise for improving clinical reasoning, but they also risk inducing automation bias, an over-reliance that can degrade diagnostic accuracy. Whether AI-trained physicians are vulnerable to this bias when LLM use is voluntary remains unknown. Objective: To determine whether exposure to erroneous LLM recommendations degrades AI-trained physicians' diagnostic performance compared to error-free AI advice. Design: A single-blind randomized clinical trial was conducted from June 20 to August 15, 2025. Setting: Physicians were recruited from multiple medical institutions in Pakistan, participating through in-person or remote video conferencing. Participants: Physicians registered with the Pakistan Medical and Dental Council with MBBS degrees, who had completed a 20-hour AI-literacy training covering LLM capabilities, prompt engineering, and critical evaluation of AI output. Intervention: Participants were randomized 1:1 to diagnose 6 clinical vignettes in 75 minutes. The control group received unmodified ChatGPT-4o's diagnostic recommendations; the treatment group's recommendations contained deliberate errors in 3 of 6 vignettes. Physicians could voluntarily consult offered ChatGPT-4o recommendations alongside conventional diagnostic resources based on their clinical judgment. Main Outcomes and Measures: Primary outcome was the diagnostic reasoning accuracy (percentage), assessed by three blinded physicians using an expert-validated rub… | F83: Qazi IA; Ali A; Khawaja AU; Akhtar MJ; Sheikh AZ; Alizai MH | G83: 2025 | H83: medRxiv | I83: 10.1101/2025.08.23.25334280 | K83: Preprint | L83: English (automatically detected) | M83: General dentistry / cross-specialty | N83: Europe PMC (Preprint); Semantic Scholar | O83: EXCLUDE | P83: E1 | Q83: physician diagnostic reasoning automation bias; medical | R83: EXCLUDE | S83: E1 | T83: physician diagnostic automation bias; not dental | U83: =IF(AND(O83=R83,O83<>"UNSURE"),"Agree","Conflict/Unsure") -> Agree | Y83: 0.165 | Z83: 1422 | AA83: No | AD83: EXCLUDE | AE83: E1 | AF83: R1 = R2
A84: LLMDENT-0250 | B84: 83 | C84: batch_01 | D84: Population-Level Oral Disease Surveillance Using Large Language Models on Clinical and Public Health Data | E84: Population-level oral disease surveillance is critical for guiding public health interventions, yet traditional systems relying solely on structured data often fail to capture contextual, behavioral, and access-to-care determinants embedded in unstructured clinical narratives. In this study, we developed a hybrid large language model (LLM) framework that integrates structured epidemiological features with embeddings derived from examination notes and survey text to improve the detection and monitoring of dental caries, periodontal disease, and tooth loss. Using the publicly available NHANES Oral Health Dataset, we compared the performance of traditional machine learning models, text-only LLM models, and our proposed hybrid approach. The hybrid model consistently outperformed all baselines, achieving higher accuracy, precision, recall, F1-score, and calibration, while maintaining equitable performance across demographic and socioeconomic subgroups. Explainability analyses revealed that combining structured and unstructured features captured clinically meaningful patterns, including behavioral risk factors and care access barriers. Our findings suggest that hybrid LLM-based surveillance can enhance real-time population-level monitoring, identify high-risk communities, and inform preventive strategies within the U.S. public healthcare system, offering a scalable, interpretable, and equitable approach to oral health monitoring. | F84: H. T. Phan; Trang Nguyen; Uyen Nguyen | G84: 2026 | H84: International Journal of Medical Science and Public Health Research | I84: 10.37547/ijmsphr/volume07issue02-03 | K84: Review (narrative) | L84: English (automatically detected) | M84: Periodontology; Restorative dentistry / cariology; Preventive dentistry / dental public health | N84: Semantic Scholar | O84: EXCLUDE | P84: E2 | Q84: hybrid LLM surveillance framework on NHANES | R84: EXCLUDE | S84: E2 | T84: hybrid LLM surveillance model on NHANES; not chatbot | U84: =IF(AND(O84=R84,O84<>"UNSURE"),"Agree","Conflict/Unsure") -> Agree | Y84: 0.078 | Z84: 1867 | AA84: No | AD84: EXCLUDE | AE84: E2 | AF84: R1 = R2
A85: LLMDENT-0709 | B85: 84 | C85: batch_01 | D85: Bridging the Skill Gap in Clinical CBCT Interpretation with CBCTRepD | E85: Generative AI has advanced rapidly in medical report generation; however, its application to oral and maxillofacial CBCT reporting remains limited, largely because of the scarcity of high-quality paired CBCT-report data and the intrinsic complexity of volumetric CBCT interpretation. To address this, we introduce CBCTRepD, a bilingual oral and maxillofacial CBCT report-generation system designed for integration into routine radiologist-AI co-authoring workflows. We curated a large-scale, high-quality paired CBCT-report dataset comprising approximately 7,408 studies, covering 55 oral disease entities across diverse acquisition settings, and used it to develop the system. We further established a clinically grounded, multi-level evaluation framework that assesses both direct AI-generated drafts and radiologist-edited collaboration reports using automatic metrics together with radiologist- and clinician-centered evaluation. Using this framework, we show that CBCTRepD achieves superior report-generation performance and produces drafts with writing quality and standardization comparable to those of intermediate radiologists. More importantly, in radiologist-AI collaboration, CBCTRepD provides consistent and clinically meaningful benefits across experience levels: it helps novice radiologists improve toward intermediate-level reporting, enables intermediate radiologists to approach senior-level performance, and even assists senior radiologists by reducing omission-related errors, in… | F85: Qinxin Wu; Fucheng Niu; Hengchuan Zhu; Yifan Sun; Yeting Shen; Xu Li; Han Wu; Leqi Liu; Zhiwen Pan; Zuozhu Liu; Fu-Dong Zhu; Bingdong Feng | G85: 2026 | H85: ArXiv | I85: 10.48550/arxiv.2603.10933 | K85: Preprint | L85: English (automatically detected) | M85: Oral & maxillofacial surgery; Oral & maxillofacial radiology | N85: Semantic Scholar; arXiv | O85: EXCLUDE | P85: E2 | Q85: custom CBCT report generation system | R85: EXCLUDE | S85: E2 | T85: CBCT report generation system | U85: =IF(AND(O85=R85,O85<>"UNSURE"),"Agree","Conflict/Unsure") -> Agree | Y85: 0.144 | Z85: 1536 | AA85: No | AD85: EXCLUDE | AE85: E2 | AF85: R1 = R2
A86: LLMDENT-1459 | B86: 85 | C86: batch_01 | D86: Performance of large language models in reporting oral health concerns and side effects in head and neck cancer: a comparative study. | E86: Abstract Purpose With increasing reliance on large language models (LLMs) for health information, this study evaluated reliability and quality, understandability, actionability, readability and misinformation risk of responses from LLMs to oral health concerns and oral side effects in head and neck cancer (HNC) patients. Methods Frequently asked questions on oral health and HNC therapy side effects were identified via ChatGPT–GPT-4-turbo and Gemini–2.5 Flash, then submitted to eight LLMs (ChatGPT–GPT-4-turbo, Gemini–2.5 Flash, Microsoft Copilot, Perplexity, Chatsonic, Mistral, Meta AI–Llama 4, DeepSeek–R1). Responses were assessed using DISCERN and modified DISCERN instruments (reliability and quality), Patient Education Materials Assessment Tool (PEMAT [understandability and actionability]), Flesch-Reading-Ease-Score (FRES [readability]), misinformation score, citations, and wordcounts. Statistical analysis was done by Scheirer-Ray-Hare-test followed by Dunn’s post-hoc-tests and Bonferroni-Holm correction (p < 0.05). Results A total of 40 questions belonging to 12 oral health-related categories were identified. Statistically significant differences between LLMs were found for DISCERN, modified DISCERN, PEMAT-understandability, PEMAT-actionability, FRES, and word counts (p < 0.001). Median DISCERN and modified DISCERN scores amounted from 47.0 (ChatGPT–GPT-4-turbo) to 59.0 (Perplexity, Chatsonic) and from 2.0 (Gemini–2.5 Flash, Mistral) to 5.0 (Perplexity) indicating good to … | F86: Rast, Jonas; Wiegand, Susanne; Biermann, Jana; Wiegand, Annette; Marschner, Felix | G86: 2025 | H86: Journal of cancer research and clinical oncology | I86: 10.1007/s00432-025-06400-w | J86: 41420748.0 | K86: Journal article (original research) | L86: English | M86: Preventive dentistry / dental public health | N86: Amass BiomedCore (connector); DOAJ; Europe PMC; PubMed/MEDLINE; Semantic Scholar | O86: INCLUDE | P86: - | Q86: oral health FAQs head neck cancer patients; 8 LLMs; DISCERN misinformation | R86: INCLUDE | S86: - | T86: oral health FAQs in head and neck cancer; eight LLMs; DISCERN misinformation | U86: =IF(AND(O86=R86,O86<>"UNSURE"),"Agree","Conflict/Unsure") -> Agree | Y86: 0.891 | Z86: 161 | AA86: No | AD86: INCLUDE | AE86: - | AF86: R1 = R2
A87: LLMDENT-2131 | B87: 86 | C87: batch_01 | D87: Assessment of treatment outcomes after using electrocautery and scalpel blade in separate patients for minor oral surgical procedure | E87: Context: Conventionally minor oral surgical treatments are done with the use of Bard Parker handle for incising the tissues. The favourability of B.P. handle is its low cost and no extra equipments. Electro surgery has many applications in oral surgery , but it is not widely used. The presence of varying information on electro surgical wound healing might be the reason. Aims: This study aimed to assess and compare the treatment outcomes in minor oral surgery done by electrocautery and scalpel blade using clinical parameters: Bleeding intraoperatively, Time taken for incision intraoperatively, Pain postoperatively, Healing of the surgical site postoperatively. Methods and Material: Sixty patients between age group ranging 15 to 65 years who reported to Dept of Oral & Maxillofacial surgery, M.G.S. Dental college underwent electrosurgery or scalpel surgery for minor oral surgical procedures under local anaesthesia, were the study subjects. They were randomly and equally divided into two groups. Statistical analysis used: Mann Whitney U test. | F87: R. Goyal; J. Akhter; G. Thapa; Pranam Nirangjan; A. Akshay; Priyadarshani Khadase | G87: 2022 | H87: International journal of health sciences | I87: 10.53730/ijhs.v6ns2.5443 | K87: Not specified | L87: English (automatically detected) | M87: Oral & maxillofacial surgery; Dental pharmacology / anesthesia | N87: Semantic Scholar | O87: EXCLUDE | P87: E2 | Q87: electrocautery vs scalpel clinical study; no LLM | R87: EXCLUDE | S87: E2 | T87: electrocautery vs scalpel clinical study; no LLM | U87: =IF(AND(O87=R87,O87<>"UNSURE"),"Agree","Conflict/Unsure") -> Agree | Y87: 0.275 | Z87: 941 | AA87: No | AD87: EXCLUDE | AE87: E2 | AF87: R1 = R2
